08_flow_control/08_02_double_tokens_flow_control/08_02_double_tokens_with_flow_control.sv
module double_tokens_with_flow_control
(
    input  clk,
    input  rst,

    input  up_valid,
    output up_ready,
    input  up_token,

    output down_valid,
    input  down_ready,
    output down_data
);

  // Task:
  // Implement module double input signals (tokens). The module must use signals valid-ready for
  // transfer tokens. If the module receives more than 100 sequential tokens then it must set up_ready = 0;

  logic [ 106:0 ]  doubled_token_buffer;
  logic [  99:0 ] original_token_buffer;

  assign up_ready   = ~original_token_buffer[ 99 ];
  assign down_valid = down_ready | up_valid;
  assign down_data  = ( doubled_token_buffer[ 0 ] | original_token_buffer[ 0 ] | ( up_token & up_valid ) );

  // Buffer loading
  always @ ( posedge clk or posedge rst )
    if   ( rst ) begin
       doubled_token_buffer <= '0;
      original_token_buffer <= '0;
    end
    else if ( up_valid & up_ready & up_token ) begin
                          doubled_token_buffer <= {  doubled_token_buffer[ 105:0 ] , 1'b1 };
      if ( ~down_ready ) original_token_buffer <= { original_token_buffer[  99:0 ] , 1'b1 };
    end
  
  // Buffer releasing
  always @ ( posedge clk )
    if ( ~up_token & down_ready )
      if      ( original_token_buffer != 0 ) original_token_buffer <= { '0 , original_token_buffer[  99:1 ] };
      else if (  doubled_token_buffer != 0 )  doubled_token_buffer <= { '0 ,  doubled_token_buffer[ 106:1 ] };

endmodule

08_flow_control/08_02_double_tokens_flow_control/testbench.sv
//----------------------------------------------------------------------------
// Testbench
//----------------------------------------------------------------------------

module testbench;

    logic clk;

    initial
    begin
        clk = '0;

        forever
            # 500 clk = ~ clk;
    end

    logic rst;

    initial
    begin
        rst <= 'x;
        repeat (2) @ (posedge clk);
        rst <= '1;
        repeat (2) @ (posedge clk);
        rst <= '0;
    end

    //------------------------------------------------------------------------

    logic up_valid;
    logic up_ready;
    logic a;

    logic down_valid;
    logic down_ready;
    logic double_a;

    int   probability;
    int   i;

    localparam N = 100 ;        // number of repetition
    localparam pos_token  = 50; // possibility generation token
    localparam pos_valid  = 50; // token's validity, as percentage
    localparam pos_ready  = 50; // possibility of readiness
    localparam N_hand     = 16; // length hand test

    // the first  nybble - a single token with handshake_up and handshake_down
    // the second nybble - a double token with handshake_up and handshake_down
    // the third  nybble - a double token without a handshake_up at the first step
    // the 4th    nybble - the two single tokens without a handshake_down
    // the 5th    nybble - no tokens but a handshake_down
    //
    // N.B. 'nybble' means 4 bits, or half a byte

    logic [0:N_hand-1] a_down_ready     =  'b1111_1111_1111_0000_1111;
    logic [0:N_hand-1] a_up_token       =  'b1000_1100_1100_1010_0000;
    logic [0:N_hand-1] a_up_valid       =  'b1111_1111_0111_1111_1111;

    logic [0:N_hand-1] a_down_data      =  'b1100_1111_0110_1111_1111;
    logic [0:N_hand-1] a_down_valid     =  'b1111_1111_1111_1111_1111;
    logic [0:N_hand-1] a_up_ready       =  'b1111_1111_1111_1111_1111;

    wire up_handshake   = up_valid & up_ready;
    wire down_handshake = down_valid & down_ready;


    double_tokens_with_flow_control i_double_tokens_with_flow_control (
        .clk        ( clk             ),
        .rst        ( rst             ),
        .up_valid   ( up_valid        ),
        .up_ready   ( up_ready        ),
        .up_token   ( a               ),
        .down_valid ( down_valid      ),
        .down_data  ( double_a        ),
        .down_ready ( down_ready      )
    );

    //------------------------------------------------------------------------

    // Monitor

    bit was_reset = 1'b0;

    always @ (posedge clk) if (rst) was_reset <= 1'b1;

    int n_orig_tokens   = 0,
        n_double_tokens = 0;

    wire in_token = up_valid & a;

    always @ (posedge clk)
    begin
        if (~ rst & was_reset &  up_handshake)
        begin
            n_orig_tokens <= n_orig_tokens + 32' (a);
        end

        if (~ rst & was_reset & down_handshake)
        begin
            n_double_tokens <= n_double_tokens + 32'(double_a);
        end
    end

    //------------------------------------------------------------------------

    initial
    begin
        `ifdef __ICARUS__
            // Uncomment the following line
            // to generate a VCD file and analyze it using GTKwave or Surfer

            $dumpvars;
        `endif

       // hand test
        @ (negedge rst);
        for ( i = 0 ; i < N_hand; i = i + 1)begin
          a          <= a_up_token[i];
          up_valid   <= a_up_valid[i];
          down_ready <= a_down_ready[i];

          @(posedge clk);
          if ((a_down_data[i] != double_a) | (a_down_valid[i] != down_valid)) begin
            $display("FAIL %s \n", `__FILE__);
            $display("Unexpected data. Step = %d\n", i);
            $display("expected double_a = %b,  down_valid = %b  \n", a_down_data[i], a_down_valid[i] );
            $display(" recived double_a = %b,  down_valid = %b  \n", double_a, down_valid );
          end
        end

        //
        repeat(N_hand)
        @(posedge clk);

        a          <= 1'b1;
        up_valid   <= 1'b1;
        down_ready <= 1'b0;
        i <= 0;

        while(up_ready) begin
          @(posedge clk)
          i <= i +1;
        end

        if (i != 100) begin
           $display("FAIL %s \n", `__FILE__);
           $display("Unexpected i = %d", i);
           $display("expected   i = %d", 100);
        end


        repeat (N)
        begin
            probability     = $urandom_range(100,0);
         //   a              <=  ($urandom_range(100,0) < pos_token);
         //   up_valid       <=  ($urandom_range(100,0) < pos_valid);

            // if the system is ready to process then generate token
            if (probability < pos_ready) begin
              down_ready     <= 1'b1;
              a              <=  ($urandom_range(100,0) < pos_token);
              up_valid       <=  ($urandom_range(100,0) < pos_valid);
            end
            else  begin
             // if system is not ready to process, then generate signal while
              down_ready   <= 1'b0;
              if ( ~(a & up_valid))
              a              <=  ($urandom_range(100,0) < pos_token);
              up_valid       <=  ($urandom_range(100,0) < pos_valid);

            end

            @ (posedge clk);
        end


        a          <= 1'b0;
        down_ready <= 1'b1;

        repeat ((2 * N) + 3)
            @ (posedge clk);


        //--------------------------------------------------------------------

        if ((n_double_tokens !== n_orig_tokens * 2) | (n_orig_tokens == 0))
        begin
            $display("FAIL %s", `__FILE__);
            $display("++ INPUT    => {%s}",
                             `PD(n_orig_tokens));

            $display("++ TEST     => {%s}",
                             `PD(n_double_tokens));
            $finish(1);
        end

        $display ("PASS %s", `__FILE__);
        $finish;
    end

endmodule

08_flow_control/08_02_double_tokens_flow_control/dump.vcd
$date
	Sun Mar 29 19:32:10 2026
$end
$version
	Icarus Verilog
$end
$timescale
	1s
$end
$scope module testbench $end
$var wire 1 ! down_handshake $end
$var wire 1 " in_token $end
$var wire 1 # up_handshake $end
$var wire 1 $ up_ready $end
$var wire 1 % down_valid $end
$var wire 1 & double_a $end
$var parameter 32 ' N $end
$var parameter 32 ( N_hand $end
$var parameter 32 ) pos_ready $end
$var parameter 32 * pos_token $end
$var parameter 32 + pos_valid $end
$var reg 1 , a $end
$var reg 16 - a_down_data [0:15] $end
$var reg 16 . a_down_ready [0:15] $end
$var reg 16 / a_down_valid [0:15] $end
$var reg 16 0 a_up_ready [0:15] $end
$var reg 16 1 a_up_token [0:15] $end
$var reg 16 2 a_up_valid [0:15] $end
$var reg 1 3 clk $end
$var reg 1 4 down_ready $end
$var reg 1 5 rst $end
$var reg 1 6 up_valid $end
$var integer 32 7 i [31:0] $end
$var integer 32 8 n_double_tokens [31:0] $end
$var integer 32 9 n_orig_tokens [31:0] $end
$var integer 32 : probability [31:0] $end
$var reg 1 ; was_reset $end
$scope module i_double_tokens_with_flow_control $end
$var wire 1 3 clk $end
$var wire 1 & down_data $end
$var wire 1 4 down_ready $end
$var wire 1 % down_valid $end
$var wire 1 5 rst $end
$var wire 1 $ up_ready $end
$var wire 1 , up_token $end
$var wire 1 6 up_valid $end
$var reg 107 < doubled_token_buffer [106:0] $end
$var reg 100 = original_token_buffer [99:0] $end
$upscope $end
$upscope $end
$enddefinitions $end
$comment Show the parameter values. $end
$dumpall
b110010 +
b110010 *
b110010 )
b10000 (
b1100100 '
$end
#0
$dumpvars
bx =
bx <
0;
b0 :
b0 9
b0 8
b0 7
x6
x5
x4
03
b1111011111111111 2
b1100110010100000 1
b1111111111111111 0
b1111111111111111 /
b1111111100001111 .
b1111011011111111 -
x,
x&
x%
x$
x#
x"
x!
$end
#500
13
#1000
03
#1500
1$
b0 =
b0 <
15
13
#2000
03
#2500
1;
13
#3000
03
#3500
1&
1!
1%
1#
1"
14
16
1,
05
13
#4000
03
#4500
b1 8
b1 9
b1 <
b1 7
13
#5000
03
#5500
0"
0,
b10 8
b10 9
b11 <
b10 7
13
#6000
03
#6500
b1 <
b11 8
b11 7
13
#7000
03
#7500
0&
0#
06
1,
b100 8
b0 <
b100 7
13
#8000
03
#8500
1&
1"
1#
16
b101 7
13
#9000
03
#9500
0"
0,
b101 8
b11 9
b1 <
b110 7
13
#10000
03
#10500
0&
b0 <
b110 8
b111 7
13
#11000
03
#11500
1&
0!
1"
04
1,
b1000 7
13
#12000
03
#12500
0"
b100 9
0,
b1 =
b1 <
b1001 7
13
#13000
03
#13500
1"
1,
b1010 7
13
#14000
03
#14500
0"
b101 9
0,
b11 =
b11 <
b1011 7
13
#15000
03
#15500
1!
14
b1100 7
13
#16000
03
#16500
b1 =
b111 8
b1101 7
13
#17000
03
#17500
b1000 8
b0 =
b1110 7
13
#18000
03
#18500
b1 <
b1001 8
b1111 7
13
#19000
03
#19500
0&
b1010 8
b0 <
b10000 7
13
#20000
03
#20500
13
#21000
03
#21500
13
#22000
03
#22500
13
#23000
03
#23500
13
#24000
03
#24500
13
#25000
03
#25500
13
#26000
03
#26500
13
#27000
03
#27500
13
#28000
03
#28500
13
#29000
03
#29500
13
#30000
03
#30500
13
#31000
03
#31500
13
#32000
03
#32500
13
#33000
03
#33500
13
#34000
03
#34500
13
#35000
03
#35500
1&
0!
1"
b0 7
04
1,
13
#36000
03
#36500
b110 9
b1 7
b1 =
b1 <
13
#37000
03
#37500
b10 7
b111 9
b11 =
b11 <
13
#38000
03
#38500
b1000 9
b11 7
b111 =
b111 <
13
#39000
03
#39500
b100 7
b1001 9
b1111 =
b1111 <
13
#40000
03
#40500
b1010 9
b101 7
b11111 =
b11111 <
13
#41000
03
#41500
b110 7
b1011 9
b111111 =
b111111 <
13
#42000
03
#42500
b1100 9
b111 7
b1111111 =
b1111111 <
13
#43000
03
#43500
b1000 7
b1101 9
b11111111 =
b11111111 <
13
#44000
03
#44500
b1110 9
b1001 7
b111111111 =
b111111111 <
13
#45000
03
#45500
b1010 7
b1111 9
b1111111111 =
b1111111111 <
13
#46000
03
#46500
b10000 9
b1011 7
b11111111111 =
b11111111111 <
13
#47000
03
#47500
b1100 7
b10001 9
b111111111111 =
b111111111111 <
13
#48000
03
#48500
b10010 9
b1101 7
b1111111111111 =
b1111111111111 <
13
#49000
03
#49500
b1110 7
b10011 9
b11111111111111 =
b11111111111111 <
13
#50000
03
#50500
b10100 9
b1111 7
b111111111111111 =
b111111111111111 <
13
#51000
03
#51500
b10000 7
b10101 9
b1111111111111111 =
b1111111111111111 <
13
#52000
03
#52500
b10110 9
b10001 7
b11111111111111111 =
b11111111111111111 <
13
#53000
03
#53500
b10010 7
b10111 9
b111111111111111111 =
b111111111111111111 <
13
#54000
03
#54500
b11000 9
b10011 7
b1111111111111111111 =
b1111111111111111111 <
13
#55000
03
#55500
b10100 7
b11001 9
b11111111111111111111 =
b11111111111111111111 <
13
#56000
03
#56500
b11010 9
b10101 7
b111111111111111111111 =
b111111111111111111111 <
13
#57000
03
#57500
b10110 7
b11011 9
b1111111111111111111111 =
b1111111111111111111111 <
13
#58000
03
#58500
b11100 9
b10111 7
b11111111111111111111111 =
b11111111111111111111111 <
13
#59000
03
#59500
b11000 7
b11101 9
b111111111111111111111111 =
b111111111111111111111111 <
13
#60000
03
#60500
b11110 9
b11001 7
b1111111111111111111111111 =
b1111111111111111111111111 <
13
#61000
03
#61500
b11010 7
b11111 9
b11111111111111111111111111 =
b11111111111111111111111111 <
13
#62000
03
#62500
b100000 9
b11011 7
b111111111111111111111111111 =
b111111111111111111111111111 <
13
#63000
03
#63500
b11100 7
b100001 9
b1111111111111111111111111111 =
b1111111111111111111111111111 <
13
#64000
03
#64500
b100010 9
b11101 7
b11111111111111111111111111111 =
b11111111111111111111111111111 <
13
#65000
03
#65500
b11110 7
b100011 9
b111111111111111111111111111111 =
b111111111111111111111111111111 <
13
#66000
03
#66500
b100100 9
b11111 7
b1111111111111111111111111111111 =
b1111111111111111111111111111111 <
13
#67000
03
#67500
b100000 7
b100101 9
b11111111111111111111111111111111 =
b11111111111111111111111111111111 <
13
#68000
03
#68500
b100110 9
b100001 7
b111111111111111111111111111111111 =
b111111111111111111111111111111111 <
13
#69000
03
#69500
b100010 7
b100111 9
b1111111111111111111111111111111111 =
b1111111111111111111111111111111111 <
13
#70000
03
#70500
b101000 9
b100011 7
b11111111111111111111111111111111111 =
b11111111111111111111111111111111111 <
13
#71000
03
#71500
b100100 7
b101001 9
b111111111111111111111111111111111111 =
b111111111111111111111111111111111111 <
13
#72000
03
#72500
b101010 9
b100101 7
b1111111111111111111111111111111111111 =
b1111111111111111111111111111111111111 <
13
#73000
03
#73500
b100110 7
b101011 9
b11111111111111111111111111111111111111 =
b11111111111111111111111111111111111111 <
13
#74000
03
#74500
b101100 9
b100111 7
b111111111111111111111111111111111111111 =
b111111111111111111111111111111111111111 <
13
#75000
03
#75500
b101000 7
b101101 9
b1111111111111111111111111111111111111111 =
b1111111111111111111111111111111111111111 <
13
#76000
03
#76500
b101110 9
b101001 7
b11111111111111111111111111111111111111111 =
b11111111111111111111111111111111111111111 <
13
#77000
03
#77500
b101010 7
b101111 9
b111111111111111111111111111111111111111111 =
b111111111111111111111111111111111111111111 <
13
#78000
03
#78500
b110000 9
b101011 7
b1111111111111111111111111111111111111111111 =
b1111111111111111111111111111111111111111111 <
13
#79000
03
#79500
b101100 7
b110001 9
b11111111111111111111111111111111111111111111 =
b11111111111111111111111111111111111111111111 <
13
#80000
03
#80500
b110010 9
b101101 7
b111111111111111111111111111111111111111111111 =
b111111111111111111111111111111111111111111111 <
13
#81000
03
#81500
b101110 7
b110011 9
b1111111111111111111111111111111111111111111111 =
b1111111111111111111111111111111111111111111111 <
13
#82000
03
#82500
b110100 9
b101111 7
b11111111111111111111111111111111111111111111111 =
b11111111111111111111111111111111111111111111111 <
13
#83000
03
#83500
b110000 7
b110101 9
b111111111111111111111111111111111111111111111111 =
b111111111111111111111111111111111111111111111111 <
13
#84000
03
#84500
b110110 9
b110001 7
b1111111111111111111111111111111111111111111111111 =
b1111111111111111111111111111111111111111111111111 <
13
#85000
03
#85500
b110010 7
b110111 9
b11111111111111111111111111111111111111111111111111 =
b11111111111111111111111111111111111111111111111111 <
13
#86000
03
#86500
b111000 9
b110011 7
b111111111111111111111111111111111111111111111111111 =
b111111111111111111111111111111111111111111111111111 <
13
#87000
03
#87500
b110100 7
b111001 9
b1111111111111111111111111111111111111111111111111111 =
b1111111111111111111111111111111111111111111111111111 <
13
#88000
03
#88500
b111010 9
b110101 7
b11111111111111111111111111111111111111111111111111111 =
b11111111111111111111111111111111111111111111111111111 <
13
#89000
03
#89500
b110110 7
b111011 9
b111111111111111111111111111111111111111111111111111111 =
b111111111111111111111111111111111111111111111111111111 <
13
#90000
03
#90500
b111100 9
b110111 7
b1111111111111111111111111111111111111111111111111111111 =
b1111111111111111111111111111111111111111111111111111111 <
13
#91000
03
#91500
b111000 7
b111101 9
b11111111111111111111111111111111111111111111111111111111 =
b11111111111111111111111111111111111111111111111111111111 <
13
#92000
03
#92500
b111110 9
b111001 7
b111111111111111111111111111111111111111111111111111111111 =
b111111111111111111111111111111111111111111111111111111111 <
13
#93000
03
#93500
b111010 7
b111111 9
b1111111111111111111111111111111111111111111111111111111111 =
b1111111111111111111111111111111111111111111111111111111111 <
13
#94000
03
#94500
b1000000 9
b111011 7
b11111111111111111111111111111111111111111111111111111111111 =
b11111111111111111111111111111111111111111111111111111111111 <
13
#95000
03
#95500
b111100 7
b1000001 9
b111111111111111111111111111111111111111111111111111111111111 =
b111111111111111111111111111111111111111111111111111111111111 <
13
#96000
03
#96500
b1000010 9
b111101 7
b1111111111111111111111111111111111111111111111111111111111111 =
b1111111111111111111111111111111111111111111111111111111111111 <
13
#97000
03
#97500
b111110 7
b1000011 9
b11111111111111111111111111111111111111111111111111111111111111 =
b11111111111111111111111111111111111111111111111111111111111111 <
13
#98000
03
#98500
b1000100 9
b111111 7
b111111111111111111111111111111111111111111111111111111111111111 =
b111111111111111111111111111111111111111111111111111111111111111 <
13
#99000
03
#99500
b1000000 7
b1000101 9
b1111111111111111111111111111111111111111111111111111111111111111 =
b1111111111111111111111111111111111111111111111111111111111111111 <
13
#100000
03
#100500
b1000110 9
b1000001 7
b11111111111111111111111111111111111111111111111111111111111111111 =
b11111111111111111111111111111111111111111111111111111111111111111 <
13
#101000
03
#101500
b1000010 7
b1000111 9
b111111111111111111111111111111111111111111111111111111111111111111 =
b111111111111111111111111111111111111111111111111111111111111111111 <
13
#102000
03
#102500
b1001000 9
b1000011 7
b1111111111111111111111111111111111111111111111111111111111111111111 =
b1111111111111111111111111111111111111111111111111111111111111111111 <
13
#103000
03
#103500
b1000100 7
b1001001 9
b11111111111111111111111111111111111111111111111111111111111111111111 =
b11111111111111111111111111111111111111111111111111111111111111111111 <
13
#104000
03
#104500
b1001010 9
b1000101 7
b111111111111111111111111111111111111111111111111111111111111111111111 =
b111111111111111111111111111111111111111111111111111111111111111111111 <
13
#105000
03
#105500
b1000110 7
b1001011 9
b1111111111111111111111111111111111111111111111111111111111111111111111 =
b1111111111111111111111111111111111111111111111111111111111111111111111 <
13
#106000
03
#106500
b1001100 9
b1000111 7
b11111111111111111111111111111111111111111111111111111111111111111111111 =
b11111111111111111111111111111111111111111111111111111111111111111111111 <
13
#107000
03
#107500
b1001000 7
b1001101 9
b111111111111111111111111111111111111111111111111111111111111111111111111 =
b111111111111111111111111111111111111111111111111111111111111111111111111 <
13
#108000
03
#108500
b1001110 9
b1001001 7
b1111111111111111111111111111111111111111111111111111111111111111111111111 =
b1111111111111111111111111111111111111111111111111111111111111111111111111 <
13
#109000
03
#109500
b1001010 7
b1001111 9
b11111111111111111111111111111111111111111111111111111111111111111111111111 =
b11111111111111111111111111111111111111111111111111111111111111111111111111 <
13
#110000
03
#110500
b1010000 9
b1001011 7
b111111111111111111111111111111111111111111111111111111111111111111111111111 =
b111111111111111111111111111111111111111111111111111111111111111111111111111 <
13
#111000
03
#111500
b1001100 7
b1010001 9
b1111111111111111111111111111111111111111111111111111111111111111111111111111 =
b1111111111111111111111111111111111111111111111111111111111111111111111111111 <
13
#112000
03
#112500
b1010010 9
b1001101 7
b11111111111111111111111111111111111111111111111111111111111111111111111111111 =
b11111111111111111111111111111111111111111111111111111111111111111111111111111 <
13
#113000
03
#113500
b1001110 7
b1010011 9
b111111111111111111111111111111111111111111111111111111111111111111111111111111 =
b111111111111111111111111111111111111111111111111111111111111111111111111111111 <
13
#114000
03
#114500
b1010100 9
b1001111 7
b1111111111111111111111111111111111111111111111111111111111111111111111111111111 =
b1111111111111111111111111111111111111111111111111111111111111111111111111111111 <
13
#115000
03
#115500
b1010000 7
b1010101 9
b11111111111111111111111111111111111111111111111111111111111111111111111111111111 =
b11111111111111111111111111111111111111111111111111111111111111111111111111111111 <
13
#116000
03
#116500
b1010110 9
b1010001 7
b111111111111111111111111111111111111111111111111111111111111111111111111111111111 =
b111111111111111111111111111111111111111111111111111111111111111111111111111111111 <
13
#117000
03
#117500
b1010010 7
b1010111 9
b1111111111111111111111111111111111111111111111111111111111111111111111111111111111 =
b1111111111111111111111111111111111111111111111111111111111111111111111111111111111 <
13
#118000
03
#118500
b1011000 9
b1010011 7
b11111111111111111111111111111111111111111111111111111111111111111111111111111111111 =
b11111111111111111111111111111111111111111111111111111111111111111111111111111111111 <
13
#119000
03
#119500
b1010100 7
b1011001 9
b111111111111111111111111111111111111111111111111111111111111111111111111111111111111 =
b111111111111111111111111111111111111111111111111111111111111111111111111111111111111 <
13
#120000
03
#120500
b1011010 9
b1010101 7
b1111111111111111111111111111111111111111111111111111111111111111111111111111111111111 =
b1111111111111111111111111111111111111111111111111111111111111111111111111111111111111 <
13
#121000
03
#121500
b1010110 7
b1011011 9
b11111111111111111111111111111111111111111111111111111111111111111111111111111111111111 =
b11111111111111111111111111111111111111111111111111111111111111111111111111111111111111 <
13
#122000
03
#122500
b1011100 9
b1010111 7
b111111111111111111111111111111111111111111111111111111111111111111111111111111111111111 =
b111111111111111111111111111111111111111111111111111111111111111111111111111111111111111 <
13
#123000
03
#123500
b1011000 7
b1011101 9
b1111111111111111111111111111111111111111111111111111111111111111111111111111111111111111 =
b1111111111111111111111111111111111111111111111111111111111111111111111111111111111111111 <
13
#124000
03
#124500
b1011110 9
b1011001 7
b11111111111111111111111111111111111111111111111111111111111111111111111111111111111111111 =
b11111111111111111111111111111111111111111111111111111111111111111111111111111111111111111 <
13
#125000
03
#125500
b1011010 7
b1011111 9
b111111111111111111111111111111111111111111111111111111111111111111111111111111111111111111 =
b111111111111111111111111111111111111111111111111111111111111111111111111111111111111111111 <
13
#126000
03
#126500
b1100000 9
b1011011 7
b1111111111111111111111111111111111111111111111111111111111111111111111111111111111111111111 =
b1111111111111111111111111111111111111111111111111111111111111111111111111111111111111111111 <
13
#127000
03
#127500
b1011100 7
b1100001 9
b11111111111111111111111111111111111111111111111111111111111111111111111111111111111111111111 =
b11111111111111111111111111111111111111111111111111111111111111111111111111111111111111111111 <
13
#128000
03
#128500
b1100010 9
b1011101 7
b111111111111111111111111111111111111111111111111111111111111111111111111111111111111111111111 =
b111111111111111111111111111111111111111111111111111111111111111111111111111111111111111111111 <
13
#129000
03
#129500
b1011110 7
b1100011 9
b1111111111111111111111111111111111111111111111111111111111111111111111111111111111111111111111 =
b1111111111111111111111111111111111111111111111111111111111111111111111111111111111111111111111 <
13
#130000
03
#130500
b1100100 9
b1011111 7
b11111111111111111111111111111111111111111111111111111111111111111111111111111111111111111111111 =
b11111111111111111111111111111111111111111111111111111111111111111111111111111111111111111111111 <
13
#131000
03
#131500
b1100000 7
b1100101 9
b111111111111111111111111111111111111111111111111111111111111111111111111111111111111111111111111 =
b111111111111111111111111111111111111111111111111111111111111111111111111111111111111111111111111 <
13
#132000
03
#132500
b1100110 9
b1100001 7
b1111111111111111111111111111111111111111111111111111111111111111111111111111111111111111111111111 =
b1111111111111111111111111111111111111111111111111111111111111111111111111111111111111111111111111 <
13
#133000
03
#133500
b1100010 7
b1100111 9
b11111111111111111111111111111111111111111111111111111111111111111111111111111111111111111111111111 =
b11111111111111111111111111111111111111111111111111111111111111111111111111111111111111111111111111 <
13
#134000
03
#134500
b1101000 9
b1100011 7
b111111111111111111111111111111111111111111111111111111111111111111111111111111111111111111111111111 =
b111111111111111111111111111111111111111111111111111111111111111111111111111111111111111111111111111 <
13
#135000
03
#135500
0#
0$
b1100100 7
b1101001 9
b1111111111111111111111111111111111111111111111111111111111111111111111111111111111111111111111111111 =
b1111111111111111111111111111111111111111111111111111111111111111111111111111111111111111111111111111 <
13
#136000
03
#136500
b1100101 7
b111001 :
13
#137000
03
#137500
0"
1!
06
14
b1 :
13
#138000
03
#138500
1"
0!
b1011 8
16
04
b1001110 :
13
#139000
03
#139500
0%
0"
06
b110010 :
13
#140000
03
#140500
0,
b1001001 :
13
#141000
03
#141500
1%
16
b1001110 :
13
#142000
03
#142500
1!
06
1,
14
b100111 :
13
#143000
03
#143500
b1100 8
b10111 :
13
#144000
03
#144500
1"
0!
b1101 8
16
04
b1100010 :
13
#145000
03
#145500
0"
1!
0,
14
b100110 :
13
#146000
03
#146500
1#
1$
1"
b111111111111111111111111111111111111111111111111111111111111111111111111111111111111111111111111111 =
b1110 8
1,
b1000 :
13
#147000
03
#147500
0!
04
b1111 8
b1101010 9
b11111111111111111111111111111111111111111111111111111111111111111111111111111111111111111111111111111 <
b110100 :
13
#148000
03
#148500
0$
0%
0"
0#
b1101011 9
06
b1111111111111111111111111111111111111111111111111111111111111111111111111111111111111111111111111111 =
b111111111111111111111111111111111111111111111111111111111111111111111111111111111111111111111111111111 <
b111000 :
13
#149000
03
#149500
1!
1"
1%
16
14
b11111 :
13
#150000
03
#150500
0"
b10000 8
06
b10 :
13
#151000
03
#151500
1"
16
b10001 8
b101010 :
13
#152000
03
#152500
0!
b10010 8
04
b111000 :
13
#153000
03
#153500
0%
0"
06
b111001 :
13
#154000
03
#154500
1!
1%
14
b101000 :
13
#155000
03
#155500
0!
16
0,
04
b10011 8
b1001101 :
13
#156000
03
#156500
0%
06
1,
b1001010 :
13
#157000
03
#157500
0,
b1010110 :
13
#158000
03
#158500
1!
1%
16
14
b100101 :
13
#159000
03
#159500
1$
06
b10100 8
b111111111111111111111111111111111111111111111111111111111111111111111111111111111111111111111111111 =
b10110 :
13
#160000
03
#160500
1#
b11111111111111111111111111111111111111111111111111111111111111111111111111111111111111111111111111 =
b10101 8
16
b1011 :
13
#161000
03
#161500
0#
0%
0!
06
04
b10110 8
b1111111111111111111111111111111111111111111111111111111111111111111111111111111111111111111111111 =
b110110 :
13
#162000
03
#162500
b1000101 :
13
#163000
03
#163500
1%
1#
16
b1001110 :
13
#164000
03
#164500
1"
1!
1,
14
b11111 :
13
#165000
03
#165500
0!
04
b10111 8
b1101100 9
b1111111111111111111111111111111111111111111111111111111111111111111111111111111111111111111111111111111 <
b1001101 :
13
#166000
03
#166500
1!
b1101101 9
14
b11111111111111111111111111111111111111111111111111111111111111111111111111111111111111111111111111 =
b11111111111111111111111111111111111111111111111111111111111111111111111111111111111111111111111111111111 <
b101001 :
13
#167000
03
#167500
0"
0#
0%
0!
06
04
b11000 8
b1101110 9
b111111111111111111111111111111111111111111111111111111111111111111111111111111111111111111111111111111111 <
b1010000 :
13
#168000
03
#168500
1!
1#
1%
16
0,
14
b100110 :
13
#169000
03
#169500
0!
04
b11001 8
b1111111111111111111111111111111111111111111111111111111111111111111111111111111111111111111111111 =
b111110 :
13
#170000
03
#170500
0%
0#
06
b1001000 :
13
#171000
03
#171500
1!
1#
1%
16
14
b101001 :
13
#172000
03
#172500
0!
b111111111111111111111111111111111111111111111111111111111111111111111111111111111111111111111111 =
b11010 8
04
b1000100 :
13
#173000
03
#173500
b111010 :
13
#174000
03
#174500
0#
1!
06
1,
14
b11100 :
13
#175000
03
#175500
1#
16
0,
b11011 8
b111 :
13
#176000
03
#176500
1"
b11111111111111111111111111111111111111111111111111111111111111111111111111111111111111111111111 =
b11100 8
1,
b1001 :
13
#177000
03
#177500
0"
0#
0%
0!
06
04
b11101 8
b1101111 9
b1111111111111111111111111111111111111111111111111111111111111111111111111111111111111111111111111111111111 <
b111111 :
13
#178000
03
#178500
1!
1%
14
b101000 :
13
#179000
03
#179500
1"
1#
0!
16
04
b11110 8
b111010 :
13
#180000
03
#180500
1!
b1110000 9
14
b111111111111111111111111111111111111111111111111111111111111111111111111111111111111111111111111 =
b11111111111111111111111111111111111111111111111111111111111111111111111111111111111111111111111111111111111 <
b10011 :
13
#181000
03
#181500
0"
0#
0%
0!
06
04
b11111 8
b1110001 9
b1001010 :
13
#182000
03
#182500
1!
1%
0,
14
b101001 :
13
#183000
03
#183500
1#
0!
16
04
b100000 8
b11111111111111111111111111111111111111111111111111111111111111111111111111111111111111111111111 =
b110101 :
13
#184000
03
#184500
0%
0#
06
1,
b110010 :
13
#185000
03
#185500
1%
1"
1#
16
b1000010 :
13
#186000
03
#186500
b1110010 9
b111111111111111111111111111111111111111111111111111111111111111111111111111111111111111111111111 =
b1010110 :
13
#187000
03
#187500
b1110011 9
b1111111111111111111111111111111111111111111111111111111111111111111111111111111111111111111111111 =
b1001010 :
13
#188000
03
#188500
0%
0"
0#
b1110100 9
06
b11111111111111111111111111111111111111111111111111111111111111111111111111111111111111111111111111 =
b1001111 :
13
#189000
03
#189500
1!
1%
14
b0 :
13
#190000
03
#190500
1#
b100001 8
16
0,
b1111 :
13
#191000
03
#191500
0#
06
b100010 8
b1111111111111111111111111111111111111111111111111111111111111111111111111111111111111111111111111 =
b10111 :
13
#192000
03
#192500
0%
0!
b111111111111111111111111111111111111111111111111111111111111111111111111111111111111111111111111 =
b100011 8
1,
04
b1001111 :
13
#193000
03
#193500
1%
1#
16
0,
b1100011 :
13
#194000
03
#194500
b1001101 :
13
#195000
03
#195500
1"
1!
1,
14
b100111 :
13
#196000
03
#196500
0!
b100100 8
b1110101 9
04
b111000 :
13
#197000
03
#197500
b1110110 9
b1111111111111111111111111111111111111111111111111111111111111111111111111111111111111111111111111 =
b111010 :
13
#198000
03
#198500
b1110111 9
b11111111111111111111111111111111111111111111111111111111111111111111111111111111111111111111111111 =
b1001101 :
13
#199000
03
#199500
0"
1!
0,
14
b1111000 9
b111111111111111111111111111111111111111111111111111111111111111111111111111111111111111111111111111 =
b1100 :
13
#200000
03
#200500
0#
b11111111111111111111111111111111111111111111111111111111111111111111111111111111111111111111111111 =
b100101 8
06
b10110 :
13
#201000
03
#201500
1#
0!
16
04
b100110 8
b1111111111111111111111111111111111111111111111111111111111111111111111111111111111111111111111111 =
b1100011 :
13
#202000
03
#202500
0#
1!
06
14
b100100 :
13
#203000
03
#203500
1#
0!
16
04
b100111 8
b111111111111111111111111111111111111111111111111111111111111111111111111111111111111111111111111 =
b1011000 :
13
#204000
03
#204500
0%
0#
06
b1001011 :
13
#205000
03
#205500
1%
1#
16
b1001010 :
13
#206000
03
#206500
1!
14
b101000 :
13
#207000
03
#207500
b101000 8
b11111111111111111111111111111111111111111111111111111111111111111111111111111111111111111111111 =
b10011 :
13
#208000
03
#208500
0#
0%
0!
b1111111111111111111111111111111111111111111111111111111111111111111111111111111111111111111111 =
b101001 8
06
1,
04
b1001101 :
13
#209000
03
#209500
1!
1%
14
b1010 :
13
#210000
03
#210500
b101010 8
b100111 :
13
#211000
03
#211500
1"
1#
16
b101011 8
b10110 :
13
#212000
03
#212500
0!
b101100 8
b1111001 9
04
b1000010 :
13
#213000
03
#213500
b1111010 9
b11111111111111111111111111111111111111111111111111111111111111111111111111111111111111111111111 =
b1010011 :
13
#214000
03
