08_flow_control/08_01_halve_tokens_with_flow_control/08_01_halve_tokens_fc.sv
module halve_tokens_with_flow_control
(
    input  clk,
    input  rst,

    input  up_valid,
    output up_ready,
    input  up_token,

    output down_valid,
    input  down_ready,
    output down_data
);

    // Task:
    // Implement a serial module that reduces amount of incoming '1' tokens by half.
    // The module must use the ready-valid protocol.
    //
    //  Expected behavior of the module
    //  1) When the input signals are up_token and up_valid is high, the signal (token) is processed.
    //  2) Every second signal received for processing is sent to the output of the module.
    //  3) When the module cannot process the signal, it sets the up_ready signal to a low level.
    //
    // Example:
    // down_ready     ->   1111_1111_1111_0000
    // up_token       ->   1101_0100_1111_1111
    // up_valid       ->   1111_1111_0101_1111
    // down_valid     ->   1111_1111_1111_1000
    // down_data      ->   0100_0100_0001_0000
    // up_ready       ->   1111_1111_0101_1000

    logic token_cnt;

    assign up_ready   = down_ready | ~token_cnt;
    assign down_valid = up_valid;
    assign down_data  = up_token   &  token_cnt & up_valid & down_ready;

    always @( posedge clk or posedge rst )
        if      ( rst )                 token_cnt <= '0;
        else if ( up_ready & up_valid ) token_cnt <= token_cnt ^ up_token;

endmodule

08_flow_control/08_01_halve_tokens_with_flow_control/testbench.sv
//----------------------------------------------------------------------------
// Testbench
//----------------------------------------------------------------------------

module testbench;

    logic clk;

    initial
    begin
        clk = '0;

        forever
            # 500 clk = ~ clk;
    end

    logic rst;

    initial
    begin
        rst <= 'x;
        repeat (2) @ (posedge clk);
        rst <= '1;
        repeat (2) @ (posedge clk);
        rst <= '0;
    end

    //------------------------------------------------------------------------

    logic up_valid;
    logic up_ready;
    logic up_token;

    logic down_valid;
    logic down_ready;
    logic down_data;

    int   probability;

    wire up_handshake   = up_valid & up_ready;
    wire down_handshake = down_valid & down_ready;


    halve_tokens_with_flow_control i_halve_tokens_with_flow_control
    (
        .clk        ( clk             ),
        .rst        ( rst             ),
        .up_valid   ( up_valid        ),
        .up_ready   ( up_ready        ),
        .up_token   ( up_token        ),
        .down_valid ( down_valid      ),
        .down_data  ( down_data       ),
        .down_ready ( down_ready      )
    );

    //------------------------------------------------------------------------

    // Number of repetitions
    localparam N = 500 ;

    // Events probability in percent
    localparam pos_token = 50;
    localparam pos_valid = 50;
    localparam pos_ready = 50;

    // Monitor
    // sample inputs
    logic[0:15] s_down_ready = 16'b1111_1111_1111_0000;
    logic[0:15] s_up_token   = 16'b1101_0100_1111_1111;
    logic[0:15] s_up_valid   = 16'b1111_1111_0101_1111;
    //outputs
    logic[0:15] s_down_valid = 16'b1111_1111_0101_1111;
    logic[0:15] s_down_data  = 16'b0100_0100_0001_0000;
    logic[0:15] s_up_ready   = 16'b1111_1111_0101_1000;

    int i;

    bit was_reset = 1'b0;


    always @ (posedge clk) if (rst) was_reset <= 1'b1;

    int n_orig_tokens = 0,
        n_half_tokens = 0;

    wire in_token = up_valid & up_token;

    always @ (posedge clk) begin
        if (~ rst & was_reset &  up_handshake)
        begin
            n_orig_tokens <= n_orig_tokens + 32' (up_token);
        end

        if (~ rst & was_reset & down_valid)
        begin
            n_half_tokens <= n_half_tokens + 32' (down_data);
        end
     end

    //------------------------------------------------------------------------
    initial
    begin
        `ifdef __ICARUS__
            // Uncomment the following line
            // to generate a VCD file and analyze it using GTKwave or Surfer

            $dumpvars;
        `endif

        @ (negedge rst);

        for ( i=0; i < 15; i = i+1 )
        begin
            down_ready <= s_down_ready[i];
            up_token   <= s_up_token[i];
            up_valid   <= s_up_valid[i];

            @(posedge  clk);

            if (~((down_ready == s_down_ready[i]) & (down_data == s_down_data[i]) & (down_valid == s_down_valid[i])))
            begin
                $display("FAIL %s", `__FILE__);
                $display ("\nERROR: numder test set = %d", i);
                $display ("\nERROR: unexpected result down_data = %h, down_ready = %h, down_valid  = %h", down_data, down_ready, down_valid);
                $display ("\n         expected result down_data = %h, down_ready = %h, down_valid  = %h", s_down_data[i], s_down_ready[i], s_down_valid[i]);
                repeat(3) @ (posedge clk);
                $finish;
            end

            // @(posedge  clk);
        end

        repeat (N)
        begin
            probability     = $urandom_range(100,0);

            // if the system is ready to process then generate token
            if (probability < pos_ready)
            begin
                down_ready     <= 1'b1;
                up_token       <=  ($urandom_range(100,0) < pos_token);
                up_valid       <=  ($urandom_range(100,0) < pos_valid);
            end
            else
            begin
                // if system is not ready to process, then generate signal while
                down_ready   <= 1'b0;
                if ( ~(up_token & up_valid))
                up_token       <=  ($urandom_range(100,0) < pos_token);
                up_valid       <=  ($urandom_range(100,0) < pos_valid);
            end

            @ (posedge clk);
        end

        up_token <= 1'b0;

        repeat (2 * N) @ (posedge clk);

        //--------------------------------------------------------------------

        if ((n_half_tokens !== n_orig_tokens / 2) | (n_orig_tokens == 0))
        begin
            $display("FAIL %s", `__FILE__);
            $display("++ INPUT    => {%s}",
                             `PD(n_orig_tokens));

            $display("++ TEST     => {%s}",
                             `PD(n_half_tokens));
            $finish(1);
        end
        $display ("PASS %s", `__FILE__);
        $finish;
    end

endmodule

08_flow_control/08_01_halve_tokens_with_flow_control/dump.vcd
$date
	Sun Mar 29 14:04:19 2026
$end
$version
	Icarus Verilog
$end
$timescale
	1s
$end
$scope module testbench $end
$var wire 1 ! down_handshake $end
$var wire 1 " in_token $end
$var wire 1 # up_handshake $end
$var wire 1 $ up_ready $end
$var wire 1 % down_valid $end
$var wire 1 & down_data $end
$var parameter 32 ' N $end
$var parameter 32 ( pos_ready $end
$var parameter 32 ) pos_token $end
$var parameter 32 * pos_valid $end
$var reg 1 + clk $end
$var reg 1 , down_ready $end
$var reg 1 - rst $end
$var reg 16 . s_down_data [0:15] $end
$var reg 16 / s_down_ready [0:15] $end
$var reg 16 0 s_down_valid [0:15] $end
$var reg 16 1 s_up_ready [0:15] $end
$var reg 16 2 s_up_token [0:15] $end
$var reg 16 3 s_up_valid [0:15] $end
$var reg 1 4 up_token $end
$var reg 1 5 up_valid $end
$var integer 32 6 i [31:0] $end
$var integer 32 7 n_half_tokens [31:0] $end
$var integer 32 8 n_orig_tokens [31:0] $end
$var integer 32 9 probability [31:0] $end
$var reg 1 : was_reset $end
$scope module i_halve_tokens_with_flow_control $end
$var wire 1 + clk $end
$var wire 1 & down_data $end
$var wire 1 , down_ready $end
$var wire 1 % down_valid $end
$var wire 1 - rst $end
$var wire 1 $ up_ready $end
$var wire 1 4 up_token $end
$var wire 1 5 up_valid $end
$var reg 1 ; token_cnt $end
$upscope $end
$upscope $end
$enddefinitions $end
$comment Show the parameter values. $end
$dumpall
b110010 *
b110010 )
b110010 (
b111110100 '
$end
#0
$dumpvars
x;
0:
b0 9
b0 8
b0 7
b0 6
x5
x4
b1111111101011111 3
b1101010011111111 2
b1111111101011000 1
b1111111101011111 0
b1111111111110000 /
b100010000010000 .
x-
x,
0+
x&
x%
x$
x#
x"
x!
$end
#500
1+
#1000
0+
#1500
0&
1$
0;
1-
1+
#2000
0+
#2500
1:
1+
#3000
0+
#3500
1#
1"
1!
1%
15
14
1,
0-
1+
#4000
0+
#4500
1&
1;
b1 8
b1 6
1+
#5000
0+
#5500
0&
0"
0;
04
b1 7
b10 8
b10 6
1+
#6000
0+
#6500
1"
14
b11 6
1+
#7000
0+
#7500
0"
1;
04
b11 8
b100 6
1+
#8000
0+
#8500
1&
1"
14
b101 6
1+
#9000
0+
#9500
0&
0"
0;
04
b10 7
b100 8
b110 6
1+
#10000
0+
#10500
b111 6
1+
#11000
0+
#11500
0!
0#
0%
05
14
b1000 6
1+
#12000
0+
#12500
1!
1"
1#
1%
15
b1001 6
1+
#13000
0+
#13500
0!
0"
0#
1;
0%
05
b101 8
b1010 6
1+
#14000
0+
#14500
1&
1!
1"
1#
1%
15
b1011 6
1+
#15000
0+
#15500
1#
1$
0&
0!
0;
0,
b11 7
b110 8
b1100 6
1+
#16000
0+
#16500
0#
0$
1;
b111 8
b1101 6
1+
#17000
0+
#17500
b1110 6
1+
#18000
0+
#18500
b111001 9
b1111 6
1+
#19000
0+
#19500
0"
1$
0&
0%
05
1,
b1 9
1+
#20000
0+
#20500
1"
0$
1%
15
0,
b1001110 9
1+
#21000
0+
#21500
0"
0%
05
b110010 9
1+
#22000
0+
#22500
04
b1001001 9
1+
#23000
0+
#23500
1%
15
b1001110 9
1+
#24000
0+
#24500
1$
0%
05
14
1,
b100111 9
1+
#25000
0+
#25500
b10111 9
1+
#26000
0+
#26500
1"
0$
1%
15
0,
b1100010 9
1+
#27000
0+
#27500
1#
0"
1$
0&
1!
04
1,
b100110 9
1+
#28000
0+
#28500
1&
1"
14
b1000 9
1+
#29000
0+
#29500
1#
1$
0&
0!
0;
0,
b100 7
b1000 8
b110100 9
1+
#30000
0+
#30500
0$
0"
0#
1;
b1001 8
0%
05
b111000 9
1+
#31000
0+
#31500
1&
1"
1#
1$
1!
1%
15
1,
b11111 9
1+
#32000
0+
#32500
0&
0!
0"
0#
0;
b101 7
b1010 8
0%
05
b10 9
1+
#33000
0+
#33500
1!
1"
1#
1%
15
b101010 9
1+
#34000
0+
#34500
0#
0$
0!
1;
b1011 8
0,
b111000 9
1+
#35000
0+
#35500
0"
0%
05
b111001 9
1+
#36000
0+
#36500
1$
1,
b101000 9
1+
#37000
0+
#37500
0$
1%
15
04
0,
b1001101 9
1+
#38000
0+
#38500
0%
05
14
b1001010 9
1+
#39000
0+
#39500
04
b1010110 9
1+
#40000
0+
#40500
1#
1$
1!
1%
15
1,
b100101 9
1+
#41000
0+
#41500
0!
0#
0%
05
b10110 9
1+
#42000
0+
#42500
1!
1#
1%
15
b1011 9
1+
#43000
0+
#43500
0#
0$
0!
0%
05
0,
b110110 9
1+
#44000
0+
#44500
b1000101 9
1+
#45000
0+
#45500
1%
15
b1001110 9
1+
#46000
0+
#46500
1&
1#
1"
1$
1!
14
1,
b11111 9
1+
#47000
0+
#47500
1#
1$
0&
0!
0;
0,
b110 7
b1100 8
b1001101 9
1+
#48000
0+
#48500
1&
1!
1;
b1101 8
1,
b101001 9
1+
#49000
0+
#49500
0"
0#
1$
0&
0!
0;
0%
05
0,
b111 7
b1110 8
b1010000 9
1+
#50000
0+
#50500
1#
1!
1%
15
04
1,
b100110 9
1+
#51000
0+
#51500
0!
0,
b111110 9
1+
#52000
0+
#52500
0#
0%
05
b1001000 9
1+
#53000
0+
#53500
1#
1!
1%
15
1,
b101001 9
1+
#54000
0+
#54500
0!
0,
b1000100 9
1+
#55000
0+
#55500
b111010 9
1+
#56000
0+
#56500
0#
0%
05
14
1,
b11100 9
1+
#57000
0+
#57500
1!
1#
1%
15
04
b111 9
1+
#58000
0+
#58500
1"
14
b1001 9
1+
#59000
0+
#59500
0$
0"
0#
0!
1;
0%
05
0,
b1111 8
b111111 9
1+
#60000
0+
#60500
1$
1,
b101000 9
1+
#61000
0+
#61500
1"
0$
1%
15
0,
b111010 9
1+
#62000
0+
#62500
1#
1$
1&
1!
1,
b10011 9
1+
#63000
0+
#63500
0"
0#
1$
0&
0!
0;
0%
05
0,
b1000 7
b10000 8
b1001010 9
1+
#64000
0+
#64500
04
1,
b101001 9
1+
#65000
0+
#65500
1#
1%
15
0,
b110101 9
1+
#66000
0+
#66500
0#
0%
05
14
b110010 9
1+
#67000
0+
#67500
1"
1#
1%
15
b1000010 9
1+
#68000
0+
#68500
0#
0$
1;
b10001 8
b1010110 9
1+
#69000
0+
#69500
b1001010 9
1+
#70000
0+
#70500
0"
0%
05
b1001111 9
1+
#71000
0+
#71500
1$
1,
b0 9
1+
#72000
0+
#72500
1!
1#
1%
15
04
b1111 9
1+
#73000
0+
#73500
0!
0#
0%
05
b10111 9
1+
#74000
0+
#74500
0$
14
0,
b1001111 9
1+
#75000
0+
#75500
1%
15
04
b1100011 9
1+
#76000
0+
#76500
b1001101 9
1+
#77000
0+
#77500
1&
1#
1"
1$
1!
14
1,
b100111 9
1+
#78000
0+
#78500
1#
1$
0&
0!
0;
b1001 7
b10010 8
0,
b111000 9
1+
#79000
0+
#79500
0#
0$
1;
b10011 8
b111010 9
1+
#80000
0+
#80500
b1001101 9
1+
#81000
0+
#81500
1#
0"
1$
0&
1!
04
1,
b1100 9
1+
#82000
0+
#82500
0!
0#
0%
05
b10110 9
1+
#83000
0+
#83500
0$
1%
15
0,
b1100011 9
1+
#84000
0+
#84500
1$
0%
05
1,
b100100 9
1+
#85000
0+
#85500
0$
1%
15
0,
b1011000 9
1+
#86000
0+
#86500
0%
05
b1001011 9
1+
#87000
0+
#87500
1%
15
b1001010 9
1+
#88000
0+
#88500
1#
1$
1!
1,
b101000 9
1+
#89000
0+
#89500
b10011 9
1+
#90000
0+
#90500
0#
0$
0!
0%
05
14
0,
b1001101 9
1+
#91000
0+
#91500
1$
1,
b1010 9
1+
#92000
0+
#92500
b100111 9
1+
#93000
0+
#93500
1&
1!
1"
1#
1%
15
b10110 9
1+
#94000
0+
#94500
1#
1$
0&
0!
0;
b1010 7
b10100 8
0,
b1000010 9
1+
#95000
0+
#95500
0#
0$
1;
b10101 8
b1010011 9
1+
#96000
0+
#96500
b110101 9
1+
#97000
0+
#97500
0"
1$
0&
0%
05
04
1,
b11111 9
1+
#98000
0+
#98500
1!
1#
1%
15
b11011 9
1+
#99000
0+
#99500
0!
0#
0%
05
b10111 9
1+
#100000
0+
#100500
0$
1%
15
0,
b110110 9
1+
#101000
0+
#101500
0%
05
b1010110 9
1+
#102000
0+
#102500
1%
15
1+
#103000
0+
#103500
0%
05
14
b1001011 9
1+
#104000
0+
#104500
1#
1$
1!
1%
15
04
1,
b101111 9
1+
#105000
0+
#105500
0#
0$
0!
0%
05
14
0,
b1001100 9
1+
#106000
0+
#106500
b1010011 9
1+
#107000
0+
#107500
1&
1"
1#
1$
1!
1%
15
1,
b110001 9
1+
#108000
0+
#108500
0"
0#
1$
0&
0!
0;
b1011 7
b10110 8
0%
05
0,
b1011010 9
1+
#109000
0+
#109500
1,
b10111 9
1+
#110000
0+
#110500
0,
b1001101 9
1+
#111000
0+
#111500
1#
1%
15
04
b1001111 9
1+
#112000
0+
#112500
1"
14
b1000001 9
1+
#113000
0+
#113500
0$
0"
0#
1;
0%
05
b10111 8
b110101 9
1+
#114000
0+
#114500
1%
15
04
b110111 9
1+
#115000
0+
#115500
1$
0%
05
14
1,
b1100 9
1+
#116000
0+
#116500
1"
0$
1%
15
0,
b1000011 9
1+
#117000
0+
#117500
0"
1$
0&
0%
05
1,
b101100 9
1+
#118000
0+
#118500
1!
1#
1%
15
04
b101010 9
1+
#119000
0+
#119500
1&
1"
14
b1011 9
1+
#120000
0+
#120500
0"
0#
1$
0&
0!
0;
b1100 7
b11000 8
0%
05
0,
b111010 9
1+
#121000
0+
#121500
04
b1011001 9
1+
#122000
0+
#122500
14
1,
b110 9
1+
#123000
0+
#123500
1!
1#
1%
15
04
b11101 9
1+
#124000
0+
#124500
0!
0#
0%
05
14
1+
#125000
0+
#125500
04
b101110 9
1+
#126000
0+
#126500
14
0,
b1010100 9
1+
#127000
0+
#127500
1"
1#
1!
1%
15
1,
b100001 9
1+
#128000
0+
#128500
0!
0#
0"
1;
b11001 8
0%
05
04
b1110 9
1+
#129000
0+
#129500
0$
14
0,
b1000010 9
1+
#130000
0+
#130500
b1100011 9
1+
#131000
0+
#131500
1$
1,
b11000 9
1+
#132000
0+
#132500
b10100 9
1+
#133000
0+
#133500
0$
04
0,
b1100001 9
1+
#134000
0+
#134500
1#
1$
1!
1%
15
1,
b111 9
1+
#135000
0+
#135500
0#
0$
0!
0%
05
0,
b1011000 9
1+
#136000
0+
#136500
1$
1,
b100010 9
1+
#137000
0+
#137500
0$
1%
15
0,
b1000101 9
1+
#138000
0+
#138500
0%
05
14
b110111 9
1+
#139000
0+
#139500
1$
04
1,
b11010 9
1+
#140000
0+
#140500
14
b11011 9
1+
#141000
0+
#141500
0$
1%
15
04
0,
b111011 9
1+
#142000
0+
#142500
1#
1$
1!
1,
b1011 9
1+
#143000
0+
#143500
0!
0#
0%
05
14
b11111 9
1+
#144000
0+
#144500
b110 9
1+
#145000
0+
#145500
1!
1#
1%
15
04
b100011 9
1+
#146000
0+
#146500
0#
1"
0$
0!
14
0,
b1000001 9
1+
#147000
0+
#147500
b110010 9
1+
#148000
0+
#148500
b1001110 9
1+
#149000
0+
#149500
0"
0%
05
b1011111 9
1+
#150000
0+
#150500
1%
15
04
b1010101 9
1+
#151000
0+
#151500
1$
0%
05
14
1,
b101100 9
1+
#152000
0+
#152500
0$
1%
15
04
0,
b1100011 9
1+
#153000
0+
#153500
b1001100 9
1+
#154000
0+
#154500
0%
05
b1001111 9
1+
#155000
0+
#155500
14
b1001100 9
1+
#156000
0+
#156500
1#
1$
1!
1%
15
04
1,
b10011 9
1+
#157000
0+
#157500
0!
0#
0%
05
14
b100000 9
1+
#158000
0+
#158500
1&
1!
1"
1#
1%
15
b11111 9
1+
#159000
0+
#159500
0&
0"
0;
04
b1101 7
b11010 8
b1100 9
1+
#160000
0+
#160500
0!
0,
b1000000 9
1+
#161000
0+
#161500
1!
1,
b100011 9
1+
#162000
0+
#162500
0!
0,
b1001110 9
1+
#163000
0+
#163500
b110101 9
1+
#164000
0+
#164500
0#
0%
05
b1001001 9
1+
#165000
0+
#165500
1#
1%
15
b1010010 9
1+
#166000
0+
#166500
0#
0%
05
14
1,
b101011 9
1+
#167000
0+
#167500
04
0,
b1010001 9
1+
#168000
0+
#168500
14
b1000001 9
1+
#169000
0+
#169500
04
1,
b101 9
1+
#170000
0+
#170500
1!
1#
1"
1%
15
14
b1000 9
1+
#171000
0+
#171500
0$
0"
0#
0!
1;
0%
05
0,
b11011 8
b111110 9
1+
#172000
0+
#172500
1#
1$
1!
1%
15
04
1,
b1000 9
1+
#173000
0+
#173500
b10000 9
1+
#174000
0+
#174500
0!
0#
0%
05
b10101 9
1+
#175000
0+
#175500
0$
1%
15
0,
b1010011 9
1+
#176000
0+
#176500
1&
1#
1"
1$
1!
14
1,
b11 9
1+
#177000
0+
#177500
0"
0#
1$
0&
0!
0;
0%
05
0,
b1110 7
b11100 8
b1000100 9
1+
#178000
0+
#178500
1#
1%
15
04
b1011011 9
1+
#179000
0+
#179500
0#
0%
05
1,
b10100 9
1+
#180000
0+
#180500
1!
1#
1%
15
b101010 9
1+
#181000
0+
#181500
1"
0!
14
0,
b1010110 9
1+
#182000
0+
#182500
0#
0"
1;
b11101 8
0%
05
04
1,
b1001 9
1+
#183000
0+
#183500
0$
0,
b1011100 9
1+
#184000
0+
#184500
b1100000 9
1+
#185000
0+
#185500
14
b1011101 9
1+
#186000
0+
#186500
1&
1"
1#
1$
1!
1%
15
1,
b100111 9
1+
#187000
0+
#187500
0&
0"
0;
04
b1111 7
b11110 8
b10100 9
1+
#188000
0+
#188500
1"
0!
14
0,
b1100011 9
1+
#189000
0+
#189500
0#
0$
1;
b11111 8
b1011111 9
1+
#190000
0+
#190500
1#
0"
1$
0&
1!
04
1,
b101111 9
1+
#191000
0+
#191500
0!
0#
0%
05
b111 9
1+
#192000
0+
#192500
14
b101100 9
1+
#193000
0+
#193500
0$
04
0,
b1001100 9
1+
#194000
0+
#194500
14
b1100001 9
1+
#195000
0+
#195500
1$
1,
b101111 9
1+
#196000
0+
#196500
1!
1#
1%
15
04
b101100 9
1+
#197000
0+
#197500
0#
1"
0$
0!
14
0,
b1100001 9
1+
#198000
0+
#198500
0"
0%
05
b1000001 9
1+
#199000
0+
#199500
04
b110110 9
1+
#200000
0+
#200500
1"
1%
15
14
b1000010 9
1+
#201000
0+
#201500
0"
1$
0&
0%
05
1,
b1011 9
1+
#202000
0+
#202500
1!
1#
1%
15
04
b101101 9
1+
#203000
0+
#203500
0#
0$
0!
0%
05
0,
b1000100 9
1+
#204000
0+
#204500
1$
14
1,
b100111 9
1+
#205000
0+
#205500
b101011 9
1+
#206000
0+
#206500
b1 9
1+
#207000
0+
#207500
1!
1#
1%
15
04
b10101 9
1+
#208000
0+
#208500
1&
1"
14
b11000 9
1+
#209000
0+
#209500
1#
1$
0&
0!
0;
0,
b10000 7
b100000 8
b1100011 9
1+
#210000
0+
#210500
0$
0"
0#
1;
b100001 8
0%
05
b111001 9
1+
#211000
0+
#211500
1"
1%
15
b1011010 9
1+
#212000
0+
#212500
1#
0"
1$
0&
1!
04
1,
b10110 9
1+
#213000
0+
#213500
0#
0$
0!
0%
05
14
0,
b1011100 9
1+
#214000
0+
#214500
1#
1$
1!
1%
15
04
1,
b100011 9
1+
#215000
0+
#215500
0#
0$
0!
0%
05
14
0,
b110101 9
1+
#216000
0+
#216500
1$
04
1,
b100 9
1+
#217000
0+
#217500
0$
1%
15
0,
b110010 9
1+
#218000
0+
#218500
0%
05
14
b1001110 9
1+
#219000
0+
#219500
1%
15
04
b1001111 9
1+
#220000
0+
#220500
0%
05
14
b1001010 9
1+
#221000
0+
#221500
1$
1,
b10 9
1+
#222000
0+
#222500
1!
1#
1%
15
04
b1000 9
1+
#223000
0+
#223500
0#
0$
0!
0,
b1011000 9
1+
#224000
0+
#224500
0%
05
14
b1000001 9
1+
#225000
0+
#225500
1&
1"
1#
1$
1!
1%
15
1,
b10010 9
1+
#226000
0+
#226500
1#
1$
0&
0!
0;
b10001 7
b100010 8
0,
b1010111 9
1+
#227000
0+
#227500
0"
0#
1;
0%
05
1,
b100011 8
b11111 9
1+
#228000
0+
#228500
1&
1!
1"
1#
1%
15
b1 9
1+
#229000
0+
#229500
0"
0#
1$
0&
0!
0;
0%
05
0,
b10010 7
b100100 8
b1010110 9
1+
#230000
0+
#230500
1"
1#
1!
1%
15
1,
b10011 9
1+
#231000
0+
#231500
1&
1;
b100101 8
b10100 9
1+
#232000
0+
#232500
0"
0#
1$
0&
0!
0;
b10011 7
b100110 8
0%
05
0,
b1000100 9
1+
#233000
0+
#233500
04
b1010111 9
1+
#234000
0+
#234500
1#
1%
15
b1001000 9
1+
#235000
0+
#235500
0#
0%
05
b1001110 9
1+
#236000
0+
#236500
14
b1011101 9
1+
#237000
0+
#237500
1"
1#
1%
15
b1010011 9
1+
#238000
0+
#238500
0#
0"
1;
b100111 8
0%
05
04
1,
b10001 9
1+
#239000
0+
#239500
0$
14
0,
b110011 9
1+
#240000
0+
#240500
1$
04
1,
b100111 9
1+
#241000
0+
#241500
0$
0,
b1011001 9
1+
#242000
0+
#242500
1$
1,
b101110 9
1+
#243000
0+
#243500
0$
0,
b1100011 9
1+
#244000
0+
#244500
1%
15
b1001000 9
1+
#245000
0+
#245500
0%
05
14
b1000111 9
1+
#246000
0+
#246500
1"
1%
15
b1010100 9
1+
#247000
0+
#247500
0"
0%
05
b1000100 9
1+
#248000
0+
#248500
1$
04
1,
b0 9
1+
#249000
0+
#249500
1"
0$
1%
15
14
0,
b111100 9
1+
#250000
0+
#250500
0"
1$
0&
0%
05
1,
b100 9
1+
#251000
0+
#251500
1!
1#
1%
15
04
b1001 9
1+
#252000
0+
#252500
0#
0$
0!
0,
b1100100 9
1+
#253000
0+
#253500
0%
05
14
b110111 9
1+
#254000
0+
#254500
1"
1%
15
b1010110 9
1+
#255000
0+
#255500
1#
1$
1&
1!
1,
b100101 9
1+
#256000
0+
#256500
0&
0!
0"
0#
0;
b10100 7
b101000 8
0%
05
b101010 9
1+
#257000
0+
#257500
1"
1#
1%
15
0,
b1001000 9
1+
#258000
0+
#258500
0#
0"
1;
b101001 8
0%
05
04
1,
b101111 9
1+
#259000
0+
#259500
0$
1%
15
0,
b111000 9
1+
#260000
0+
#260500
1$
0%
05
14
1,
b1000 9
1+
#261000
0+
#261500
1!
1#
1%
15
04
b0 9
1+
#262000
0+
#262500
1&
1"
14
b1100 9
1+
#263000
0+
#263500
1#
1$
0&
0!
0;
0,
b10101 7
b101010 8
b1010101 9
1+
#264000
0+
#264500
0#
0$
1;
b101011 8
b110110 9
1+
#265000
0+
#265500
0"
1$
0&
0%
05
04
1,
b100110 9
1+
#266000
0+
#266500
0$
1%
15
0,
b1100010 9
1+
#267000
0+
#267500
1"
14
b110111 9
1+
#268000
0+
#268500
b111010 9
1+
#269000
0+
#269500
1#
1$
1&
1!
1,
b101010 9
1+
#270000
0+
#270500
1#
1$
0&
0!
0;
b10110 7
b101100 8
0,
b110011 9
1+
#271000
0+
#271500
0#
0$
1;
b101101 8
b1001110 9
1+
#272000
0+
#272500
b1001100 9
1+
#273000
0+
#273500
1#
1$
1&
1!
1,
b100111 9
1+
#274000
0+
#274500
0"
0#
1$
0&
0!
0;
b10111 7
b101110 8
0%
05
0,
b111110 9
1+
#275000
0+
#275500
1#
1%
15
04
b1000011 9
1+
#276000
0+
#276500
0#
0%
05
b1011110 9
1+
#277000
0+
#277500
b110010 9
1+
#278000
0+
#278500
1,
b11111 9
1+
#279000
0+
#279500
1#
1"
1%
15
14
0,
b1000101 9
1+
#280000
0+
#280500
0#
0$
1;
b101111 8
b111011 9
1+
#281000
0+
#281500
1#
1$
1&
1!
1,
b10101 9
1+
#282000
0+
#282500
0"
0#
1$
0&
0!
0;
b11000 7
b110000 8
0%
05
0,
b110100 9
1+
#283000
0+
#283500
04
b110110 9
1+
#284000
0+
#284500
14
b1000011 9
1+
#285000
0+
#285500
1"
1#
1!
1%
15
1,
b100110 9
1+
#286000
0+
#286500
0"
1;
b110001 8
04
b10111 9
1+
#287000
0+
#287500
0#
0$
0!
0%
05
0,
b111001 9
1+
#288000
0+
#288500
1%
15
1+
#289000
0+
#289500
1#
1$
1!
1,
b11001 9
1+
#290000
0+
#290500
b111 9
1+
#291000
0+
#291500
0#
0$
0!
0,
b1001001 9
1+
#292000
0+
#292500
1"
14
b111101 9
1+
#293000
0+
#293500
0"
1$
0&
0%
05
1,
b1111 9
1+
#294000
0+
#294500
0$
04
0,
b1000110 9
1+
#295000
0+
#295500
1&
1#
1"
1$
1!
1%
15
14
1,
b10000 9
1+
#296000
0+
#296500
1#
1$
0&
0!
0;
b11001 7
b110010 8
0,
b1000000 9
1+
#297000
0+
#297500
0#
0$
1;
b110011 8
b1100011 9
1+
#298000
0+
#298500
0"
0%
05
b1000010 9
1+
#299000
0+
#299500
04
b1010001 9
1+
#300000
0+
#300500
1#
1$
1!
1%
15
1,
b110001 9
1+
#301000
0+
#301500
1&
1"
14
b100 9
1+
#302000
0+
#302500
1#
1$
0&
0!
0;
b11010 7
b110100 8
0,
b1000101 9
1+
#303000
0+
#303500
0$
0"
0#
1;
0%
05
b110101 8
b1000011 9
1+
#304000
0+
#304500
1&
1"
1#
1$
1!
1%
15
1,
b10 9
1+
#305000
0+
#305500
0"
0#
1$
0&
0!
0;
0%
05
0,
b11011 7
b110110 8
b111010 9
1+
#306000
0+
#306500
04
b1000011 9
1+
#307000
0+
#307500
b1011100 9
1+
#308000
0+
#308500
1#
1"
1%
15
14
1+
#309000
0+
#309500
0#
0$
1;
b110111 8
b1010010 9
1+
#310000
0+
#310500
0"
0%
05
b1011000 9
1+
#311000
0+
#311500
1#
1$
1!
1%
15
04
1,
b10111 9
1+
#312000
0+
#312500
0!
0#
0%
05
b110001 9
1+
#313000
0+
#313500
1!
1#
1%
15
b1111 9
1+
#314000
0+
#314500
1&
1"
14
b100101 9
1+
#315000
0+
#315500
0&
0;
b11100 7
b111000 8
b10100 9
1+
#316000
0+
#316500
0!
0#
0"
1;
b111001 8
0%
05
04
b11010 9
1+
#317000
0+
#317500
0$
0,
b1011000 9
1+
#318000
0+
#318500
1&
1#
1"
1$
1!
1%
15
14
1,
b100100 9
1+
#319000
0+
#319500
1#
1$
0&
0!
0;
0,
b11101 7
b111010 8
b1011000 9
1+
#320000
0+
#320500
0$
0"
0#
1;
b111011 8
0%
05
b1001000 9
1+
#321000
0+
#321500
1"
1%
15
b1000101 9
1+
#322000
0+
#322500
0"
1$
0&
0%
05
1,
b11100 9
1+
#323000
0+
#323500
1!
1#
1%
15
04
b11000 9
1+
#324000
0+
#324500
0!
0#
0%
05
b1110 9
1+
#325000
0+
#325500
0$
14
0,
b1001100 9
1+
#326000
0+
#326500
1"
1%
15
b1010000 9
1+
#327000
0+
#327500
b1011111 9
1+
#328000
0+
#328500
b110011 9
1+
#329000
0+
#329500
b1100100 9
1+
#330000
0+
#330500
1#
0"
1$
0&
1!
04
1,
b100110 9
1+
#331000
0+
#331500
0#
0$
0!
0,
b1001001 9
1+
#332000
0+
#332500
0%
05
b110010 9
1+
#333000
0+
#333500
1"
1%
15
14
b1011111 9
1+
#334000
0+
#334500
0"
1$
0&
0%
05
04
1,
b11110 9
1+
#335000
0+
#335500
0$
0,
b1100010 9
1+
#336000
0+
#336500
14
b1010110 9
1+
#337000
0+
#337500
1$
04
1,
b11 9
1+
#338000
0+
#338500
0$
14
0,
b111110 9
1+
#339000
0+
#339500
1"
1%
15
b111100 9
1+
#340000
0+
#340500
1#
1$
1&
1!
1,
b101111 9
1+
#341000
0+
#341500
0&
0;
b11110 7
b111100 8
b101101 9
1+
#342000
0+
#342500
0!
0"
0#
1;
b111101 8
0%
05
b110001 9
1+
#343000
0+
#343500
1&
1!
1"
1#
1%
15
b100011 9
1+
#344000
0+
#344500
0&
0!
0#
0"
0;
b11111 7
b111110 8
0%
05
04
b11 9
1+
#345000
0+
#345500
1!
1#
1"
1%
15
14
b110001 9
1+
#346000
0+
#346500
0"
1;
b111111 8
04
b110 9
1+
#347000
0+
#347500
0#
0$
0!
0,
b1001010 9
1+
#348000
0+
#348500
1#
1$
1!
1,
b101110 9
1+
#349000
0+
#349500
0!
0#
0%
05
b10010 9
1+
#350000
0+
#350500
b11011 9
1+
#351000
0+
#351500
14
b11001 9
1+
#352000
0+
#352500
04
b1110 9
1+
#353000
0+
#353500
14
b101100 9
1+
#354000
0+
#354500
1"
0$
1%
15
0,
b110111 9
1+
#355000
0+
#355500
0"
0%
05
b1100010 9
1+
#356000
0+
#356500
1%
15
04
b1000100 9
1+
#357000
0+
