06_pipelining/06_07_put_in_order/06_07_put_in_order.sv
module put_in_order
# (
    parameter width    = 16,
              n_inputs = 4
)
(
    input                       clk,
    input                       rst,

    input  [ n_inputs - 1 : 0 ] up_vlds,
    input  [ n_inputs - 1 : 0 ]
           [ width    - 1 : 0 ] up_data,

    output                      down_vld,
    output [ width   - 1 : 0 ]  down_data
);

    // Task:
    //
    // Implement a module that accepts many outputs of the computational blocks
    // and outputs them one by one in order. Input signals "up_vlds" and "up_data"
    // are coming from an array of non-pipelined computational blocks.
    // These external computational blocks have a variable latency.
    //
    // The order of incoming "up_vlds" is not determent, and the task is to
    // output "down_vld" and corresponding data in a round-robin manner,
    // one after another, in order.
    //
    // Comment:
    // The idea of the block is kinda similar to the "parallel_to_serial" block
    // from Homework 2, but here block should also preserve the output order.


endmodule

06_pipelining/06_07_put_in_order/testbench_2.sv
`include "util.svh"

module testbench_2;

    // Clock and reset

    logic clk;

    initial
    begin
        clk = '0;

        forever
            # 500 clk = ~ clk;
    end

    logic rst;

    initial
    begin
        rst <= 'x;
        repeat (2) @ (posedge clk);
        rst <= '1;
        repeat (2) @ (posedge clk);
        rst <= '0;
    end

    bit was_reset = 1'b0;

    always @ (posedge clk)
        if (rst)
            was_reset <= 1'b1;

    //------------------------------------------------------------------------

    // Instantiation

    localparam width = 8, n_inputs = 10;

    logic [n_inputs - 1:0] up_vlds;

    logic [n_inputs - 1:0]
          [width    - 1:0] up_data;

    wire                   down_vld;
    wire  [width    - 1:0] down_data;

    put_in_order
    # (
        .width    ( width    ),
        .n_inputs ( n_inputs )
    )
    i_put_in_order (.*);

    //------------------------------------------------------------------------

    logic [width - 1:0] queue [$];
    logic [width - 1:0] down_data_expected;

    task receive ();

        forever
        begin
            @ (posedge clk);

            if (down_vld)
            begin
                if (queue.size () == 0)
                begin
                    $display ("FAIL %s", `__FILE__);

                    $display ("++ TEST     => {%s}",
                        `PD (queue.size ()));

                    $finish (1);
                end
                else
                begin
                    down_data_expected = queue.pop_front ();

                    if (down_data !== down_data_expected)
                    begin
                        $display ("FAIL %s", `__FILE__);

                        $display ("++ TEST     => {%s, %s}",
                            `PH (down_data), `PH (down_data_expected));

                        $finish (1);
                    end
                end
            end
        end

    endtask

    //------------------------------------------------------------------------

    int unsigned counter = 0;

    localparam ptr_width = $clog2 (n_inputs);
    localparam [ptr_width - 1:0] max_ptr = n_inputs - 1;

    localparam latency_width = $clog2 (n_inputs + 1);         // TODO: think
    localparam [latency_width - 1:0] max_latency = n_inputs;  // TODO: think

    logic [ptr_width - 1:0] ptr;

    logic [n_inputs - 1:0]                      pending;
    logic [n_inputs - 1:0][width         - 1:0] pending_data;
    logic [n_inputs - 1:0][latency_width - 1:0] pending_latency;

    logic [n_inputs - 1:0]                      pending_for_log;
    logic [n_inputs - 1:0][width         - 1:0] pending_data_for_log;

    task send (int n_reps);

        ptr     = '0;
        pending = '0;

        for (int rep = 0; rep < n_reps || pending != '0; rep ++)
        begin
            for (int i = 0; i < n_inputs; i ++)
                if (pending_latency [i] > 0)
                    pending_latency [i] --;

            //----------------------------------------------------------------

            if ($urandom_range (0, 100) < 80)
            begin
                assert (~ pending [ptr]);

                pending [ptr] = 1'b1;

                if (counter < n_inputs * 3)
                    pending_data [ptr] = counter ++;
                else
                    pending_data [ptr] = $urandom ();

                pending_latency [ptr] = $urandom_range (0, max_latency - 1);

                queue.push_back (pending_data [ptr]);

                if (ptr == max_ptr) ptr = '0; else ptr ++;
            end

            //----------------------------------------------------------------

            up_vlds <= '0;
            up_data <= 'x;

            for (int i = 0; i < n_inputs; i ++)
            begin
                if (pending [i] && pending_latency [i] == 0)
                begin
                    pending [i] = 1'b0;

                    up_vlds [i] <= 1'b1;
                    up_data [i] <= pending_data [i];
                end
            end

            // Pending for log is needed to avoid race condition.
            // Race condition may happen because of blocking assignments

            pending_for_log      <= pending;
            pending_data_for_log <= pending_data;

            @ (posedge clk);
        end

        up_vlds <= '0;
        up_data <= 'x;

        repeat (n_inputs) @ (posedge clk);

    endtask

    //------------------------------------------------------------------------

    int unsigned cycle = 0;

    always @ (posedge clk)
    begin
        if (was_reset)
        begin
            $write ("%3d  pending  ", cycle);

            for (int i = 0; i < n_inputs; i ++)
                if (pending_for_log [i])
                    $write (" %h", pending_data_for_log [i]);
                else
                    $write ("   ");

            $display;

            $write ("%3d  up       ", cycle);

            for (int i = 0; i < n_inputs; i ++)
                if (up_vlds [i])
                    $write (" %h", up_data [i]);
                else
                    $write ("   ");

            $display;

            $write ("%3d  down     ", cycle);

            if (down_vld)
                $write (" %h", down_data);

            $display ("\n");
        end

        cycle ++;
    end

    //------------------------------------------------------------------------

    localparam TIMEOUT = 10000;

    task run ();

        `ifdef __ICARUS__
            // Uncomment the following line
            // to generate a VCD file and analyze it using GTKwave or Surfer

            //$dumpvars;
        `endif

        @ (negedge rst);

        fork
            send (1000);
            receive ();

            begin
                repeat (TIMEOUT) @ (posedge clk);
                $display ("FAIL: timeout!");
                $finish (1);
            end
        join_any

        $display ("\nPASS %s", `__FILE__);

    endtask

endmodule

06_pipelining/06_07_put_in_order/delay_data_model.sv
//This block emulate non-constant processing delay
//Delay variable from 1 to n_input clock cycles

// *****************************************************************************
// FOR SIMULATION PURPOSES ONLY!
//
// NOT SUITABLE FOR SYNTHESIS!
// *****************************************************************************

module delay_data_model
#(
    parameter width    = 16,
              n_inputs = 5,
              delay_width = $clog2( n_inputs )
)
(
    input                         clk,
    input                         rst,

    input                         vld_in,
    input [ delay_width - 1 : 0 ] out_delay,
    input [ width-1 : 0 ]         data_in,

    output logic                  vld_out,
    output logic [ width-1 : 0 ]  data_out
);

    logic [ delay_width - 1 : 0 ] delay;
    logic [ width - 1 : 0 ]       data_lock;
    logic                         ready;
    event                         delay_done;

    //Input
    initial begin
        data_lock  <= '0;
        delay      <= '0;
        ready      <= '1;
        @(!rst);

        forever begin

            while( ~vld_in ) @( posedge clk );
            ready     <= '0;
            data_lock <= data_in;
            delay     <= out_delay;

            repeat ( 32' ( delay ) ) @( posedge clk );

            ready <= 1'b1;

            @( posedge clk );
            -> delay_done;
        end
    end

    //output
    initial begin
        vld_out   <= '0;
        data_out  <= '0;
        @( !rst )

        forever begin
            //Output locked data when finished wait
            @( delay_done );
            vld_out  <= 1'b1;
            data_out <= data_lock;
            //Hold vld_out for one clk
            @( posedge clk );
            vld_out  <= 1'b0;
        end
    end

    //Self check - repeated vld_in when module in process delay forbidden
    initial begin
        forever begin
            @( posedge clk );
            if ( vld_in && !ready ) begin
            $warning("Repeated vld_in when block in process. Current vld_in will be ignored. Time: ", $realtime);
            end
        end
    end

endmodule

06_pipelining/06_07_put_in_order/testbench_1.sv
module testbench_1;

  localparam  width          = 16,
              n_inputs       = 4,
              data_ptr_width = $clog2( n_inputs );

  logic                                       clk;
  logic                                       rst;
  logic [ n_inputs - 1 : 0 ]                  up_vlds;
  logic [ n_inputs - 1 : 0 ][ width - 1 : 0 ] up_data;
  logic                                       down_vld;
  logic [ width - 1 : 0 ]                     down_data;

  put_in_order #( .width( width ), .n_inputs( n_inputs ) )
  DUT(
    .clk        ( clk       ),
    .rst        ( rst       ),
    .up_vlds    ( up_vlds   ),
    .up_data    ( up_data   ),
    .down_vld   ( down_vld  ),
    .down_data  ( down_data )
  );


  //--------------------------------------------------------------------------
  // Driving clk

  initial
  begin

    clk = '1;
    forever # 5 clk = ~ clk;

  end

  //------------------------------------------------------------------------
  // Reset

  task reset ();

    rst <= 'x;
    repeat ( 3 ) @ ( posedge clk );
    rst <= '1;
    repeat ( 3 ) @ ( posedge clk );
    rst <= '0;

  endtask

  //------------------------------------------------------------------------

  logic                            running;
  logic [ width - 1 : 0 ]          current_data;
  logic [ n_inputs - 1 : 0 ]       ring_one;
  logic [ data_ptr_width - 1 : 0 ] data_ptr;

  //Pointer to current valid data input
  initial begin

    data_ptr <= '0;

    wait ( running ) @( posedge clk );

    forever begin
      data_ptr <= data_ptr + 1'b1;
      if ( data_ptr >= data_ptr_width' ( n_inputs - 1 ) )
        data_ptr <= '0;

      @( posedge clk );
    end

  end

  //current valid bit
  always_comb begin
    ring_one           = '0;
    if ( running ) begin
      ring_one             = '0;
      ring_one[ data_ptr ] = 1'b1;
    end
  end

  //Input data generation
  always_ff @( posedge clk ) begin
    if ( rst ) begin
      current_data <= '0;
    end else begin
      if ( running )
        current_data <= current_data + 1'b1;
    end
  end

  //delay generation
  logic [ n_inputs : 0 ][ data_ptr_width : 0 ] delays;
  event all_combination_done;

  initial begin

    delays = '0;

    wait ( running ) @( posedge clk );

    forever begin

      //get new delays value on every n_inputs cycle
      repeat ( n_inputs ) @( posedge clk );

      delays[ 0 ] = delays[ 0 ] + 1'b1;

      for ( int i = 0; i < n_inputs; i = i + 1 ) begin
        if ( delays[ i ] >= n_inputs ) begin
          delays[ i ]     = '0;
          delays[ i + 1 ] = delays[ i + 1 ] + 1'b1;
        end
      end

      //When overflow in last delay variable ( delays[n_inputs - 1] ) occure
      //we get "1" in delays[n_inputs]. This meant end of generation
      if ( delays[ n_inputs ] > '0 )
        -> all_combination_done;

    end


  end

  //Generate blocks that simulate modules with given latency
  genvar i;
  generate
    for ( i = 0; i < n_inputs; i++ ) begin : input_generator
      delay_data_model #( .width( width ), .n_inputs( n_inputs ) )
      r_delay(
        .clk       ( clk          ),
        .rst       ( rst          ),
        .vld_in    ( ring_one[i]  ),
        .out_delay ( delays[i][(data_ptr_width - 1) : 0] ),
        .data_in   ( current_data ),
        .vld_out   ( up_vlds[i]   ),
        .data_out  ( up_data[i]   )
      );
    end
  endgenerate

  event finish;

  initial
  begin
    `ifdef __ICARUS__
        // Uncomment the following line
        // to generate a VCD file and analyze it using GTKwave

        $dumpvars;
    `endif

    running <= 1'b0;
    reset();
    running <= 1'b1;

    //wait until all combination will be generated
    @( all_combination_done );
    running <= 1'b0;

    //Giving time for finishing pending delays
    repeat ( n_inputs + 1 ) @( posedge clk );

    -> finish;

    //Give time finish work for final block
    @( posedge clk );

    $finish;

  end

  //Collect input data
  logic  [ width - 1 : 0 ] data_in_queue [$];

  initial begin

    forever begin

      @( posedge clk );
      if ( running )
        data_in_queue.push_back( current_data );

    end

  end

  //Collect output data
  logic  [ width - 1 : 0 ] data_out_queue [$];

  initial begin

    forever begin

      @( posedge clk )
      if ( down_vld )
        data_out_queue.push_back( down_data );

    end

  end

  //Check data - last block. in "final" block for cycle not executed for some reason
  logic [ width - 1 : 0 ] res_expected;
  logic [ width - 1 : 0 ] res;
  logic                   is_test_fail;
  initial begin

    @( finish );
    is_test_fail = '0;

    $info("Qeueue size: %d", data_in_queue.size() );

    for ( int l = 0; l < data_in_queue.size(); l = l + 1 ) begin
      res_expected = data_in_queue.pop_front ();
      res          = data_out_queue.pop_front ();

      if ( res_expected !== res ) begin
        $warning( "Test failed. Expected output %d, but get %d", res_expected, res );
        is_test_fail  = 1'b1;
      end
    end

    if ( is_test_fail )
      $display ( "FAIL %s - see above", `__FILE__ );
    else
      $display ( "PASS %s", `__FILE__ );

  end

endmodule

06_pipelining/06_07_put_in_order/testbench.sv
module testbench;

    testbench_1 tb_1 ();
    testbench_2 tb_2 ();

    initial
    begin
        // First, prevent tb_1 from running by stalling its clock

        force tb_1.clk = '0;

        // Now run tb_2

        tb_2.run ();

        // Finally, let tb_1 to run

        release tb_1.clk;
    end

endmodule

06_pipelining/dump.vcd
$date
	Sun Feb 22 01:57:07 2026
$end
$version
	Icarus Verilog
$end
$timescale
	1s
$end
$scope module testbench $end
$scope module tb_1 $end
$var event 1 ! finish $end
$var event 1 " all_combination_done $end
$var wire 16 # down_data [15:0] $end
$var wire 1 $ down_vld $end
$var wire 4 % up_vlds [3:0] $end
$var wire 64 & up_data [63:0] $end
$var parameter 32 ' data_ptr_width $end
$var parameter 32 ( n_inputs $end
$var parameter 32 ) width $end
$var reg 1 * clk $end
$var reg 16 + current_data [15:0] $end
$var reg 2 , data_ptr [1:0] $end
$var reg 15 - delays [14:0] $end
$var reg 1 . is_test_fail $end
$var reg 16 / res [15:0] $end
$var reg 16 0 res_expected [15:0] $end
$var reg 4 1 ring_one [3:0] $end
$var reg 1 2 rst $end
$var reg 1 3 running $end
$scope begin input_generator[0] $end
$var parameter 2 4 i $end
$scope module r_delay $end
$var event 1 5 delay_done $end
$var wire 1 * clk $end
$var wire 16 6 data_in [15:0] $end
$var wire 2 7 out_delay [1:0] $end
$var wire 1 2 rst $end
$var wire 1 8 vld_in $end
$var parameter 32 9 delay_width $end
$var parameter 32 : n_inputs $end
$var parameter 32 ; width $end
$var reg 16 < data_lock [15:0] $end
$var reg 16 = data_out [15:0] $end
$var reg 2 > delay [1:0] $end
$var reg 1 ? ready $end
$var reg 1 @ vld_out $end
$upscope $end
$upscope $end
$scope begin input_generator[1] $end
$var parameter 2 A i $end
$scope module r_delay $end
$var event 1 B delay_done $end
$var wire 1 * clk $end
$var wire 16 C data_in [15:0] $end
$var wire 2 D out_delay [1:0] $end
$var wire 1 2 rst $end
$var wire 1 E vld_in $end
$var parameter 32 F delay_width $end
$var parameter 32 G n_inputs $end
$var parameter 32 H width $end
$var reg 16 I data_lock [15:0] $end
$var reg 16 J data_out [15:0] $end
$var reg 2 K delay [1:0] $end
$var reg 1 L ready $end
$var reg 1 M vld_out $end
$upscope $end
$upscope $end
$scope begin input_generator[2] $end
$var parameter 3 N i $end
$scope module r_delay $end
$var event 1 O delay_done $end
$var wire 1 * clk $end
$var wire 16 P data_in [15:0] $end
$var wire 2 Q out_delay [1:0] $end
$var wire 1 2 rst $end
$var wire 1 R vld_in $end
$var parameter 32 S delay_width $end
$var parameter 32 T n_inputs $end
$var parameter 32 U width $end
$var reg 16 V data_lock [15:0] $end
$var reg 16 W data_out [15:0] $end
$var reg 2 X delay [1:0] $end
$var reg 1 Y ready $end
$var reg 1 Z vld_out $end
$upscope $end
$upscope $end
$scope begin input_generator[3] $end
$var parameter 3 [ i $end
$scope module r_delay $end
$var event 1 \ delay_done $end
$var wire 1 * clk $end
$var wire 16 ] data_in [15:0] $end
$var wire 2 ^ out_delay [1:0] $end
$var wire 1 2 rst $end
$var wire 1 _ vld_in $end
$var parameter 32 ` delay_width $end
$var parameter 32 a n_inputs $end
$var parameter 32 b width $end
$var reg 16 c data_lock [15:0] $end
$var reg 16 d data_out [15:0] $end
$var reg 2 e delay [1:0] $end
$var reg 1 f ready $end
$var reg 1 g vld_out $end
$upscope $end
$upscope $end
$scope module DUT $end
$var wire 1 * clk $end
$var wire 16 h down_data [15:0] $end
$var wire 1 $ down_vld $end
$var wire 1 2 rst $end
$var wire 64 i up_data [63:0] $end
$var wire 4 j up_vlds [3:0] $end
$var parameter 32 k n_inputs $end
$var parameter 32 l width $end
$upscope $end
$scope begin $ivl_for_loop0 $end
$var integer 32 m i [31:0] $end
$upscope $end
$scope begin $ivl_for_loop1 $end
$var integer 32 n l [31:0] $end
$upscope $end
$scope task reset $end
$upscope $end
$upscope $end
$scope module tb_2 $end
$var wire 8 o down_data [7:0] $end
$var wire 1 p down_vld $end
$var parameter 32 q TIMEOUT $end
$var parameter 32 r latency_width $end
$var parameter 4 s max_latency $end
$var parameter 4 t max_ptr $end
$var parameter 32 u n_inputs $end
$var parameter 32 v ptr_width $end
$var parameter 32 w width $end
$var reg 1 x clk $end
$var reg 8 y down_data_expected [7:0] $end
$var reg 10 z pending [9:0] $end
$var reg 80 { pending_data [79:0] $end
$var reg 80 | pending_data_for_log [79:0] $end
$var reg 10 } pending_for_log [9:0] $end
$var reg 40 ~ pending_latency [39:0] $end
$var reg 4 !" ptr [3:0] $end
$var reg 1 "" rst $end
$var reg 80 #" up_data [79:0] $end
$var reg 10 $" up_vlds [9:0] $end
$var reg 32 %" counter [31:0] $end
$var reg 32 &" cycle [31:0] $end
$var reg 1 '" was_reset $end
$scope module i_put_in_order $end
$var wire 1 x clk $end
$var wire 8 (" down_data [7:0] $end
$var wire 1 p down_vld $end
$var wire 1 "" rst $end
$var wire 80 )" up_data [79:0] $end
$var wire 10 *" up_vlds [9:0] $end
$var parameter 32 +" n_inputs $end
$var parameter 32 ," width $end
$upscope $end
$scope begin $ivl_for_loop5 $end
$var integer 32 -" i [31:0] $end
$upscope $end
$scope begin $ivl_for_loop6 $end
$var integer 32 ." i [31:0] $end
$upscope $end
$scope task receive $end
$upscope $end
$scope task run $end
$upscope $end
$scope task send $end
$var integer 32 /" n_reps [31:0] $end
$scope begin $ivl_for_loop2 $end
$var integer 32 0" rep [31:0] $end
$scope begin $ivl_for_loop3 $end
$var integer 32 1" i [31:0] $end
$upscope $end
$scope begin $ivl_for_loop4 $end
$var integer 32 2" i [31:0] $end
$upscope $end
$upscope $end
$upscope $end
$upscope $end
$upscope $end
$enddefinitions $end
$comment Show the parameter values. $end
$dumpall
b1000 ,"
b1010 +"
b1000 w
b100 v
b1010 u
b1001 t
b1010 s
b100 r
b10011100010000 q
b10000 l
b100 k
b10000 b
b100 a
b10 `
b11 [
b10000 U
b100 T
b10 S
b10 N
b10000 H
b100 G
b10 F
b1 A
b10000 ;
b100 :
b10 9
b0 4
b10000 )
b100 (
b10 '
$end
#0
$dumpvars
b0 2"
b0 1"
b0 0"
b0 /"
b0 ."
b0 -"
bx *"
bx )"
bz ("
0'"
b0 &"
b0 %"
bx $"
bx #"
x""
bx !"
bx ~
bx }
bx |
bx {
bx z
bx y
0x
zp
bz o
b0 n
b0 m
b0 j
b0 i
bz h
0g
1f
b0 e
b0 d
b0 c
0_
b0 ^
bx ]
1\
0Z
1Y
b0 X
b0 W
b0 V
0R
b0 Q
bx P
1O
0M
1L
b0 K
b0 J
b0 I
0E
b0 D
bx C
1B
0@
1?
b0 >
b0 =
b0 <
08
b0 7
bx 6
15
03
x2
b0 1
bx 0
bx /
x.
b0 -
b0 ,
bx +
0*
b0 &
b0 %
z$
bz #
1"
1!
$end
#500
b1 &"
1x
#1000
0x
#1500
1""
b10 &"
1x
#2000
0x
#2500
1'"
b11 &"
1x
#3000
0x
#3500
bx00000000 |
b1 }
b0 $"
b0 *"
b1010 2"
bx0010 ~
bx00000000 {
b1 %"
b1010 1"
b1 z
b1 !"
b1111101000 /"
0""
b100 &"
b1010 ."
b1010 -"
1x
#4000
0x
#4500
bx0000000100000000 |
b11 }
b1010 2"
b10 !"
bx0000000100000000 {
b10 %"
b11 z
bx00010001 ~
b1010 1"
b101 &"
b1010 ."
b1010 -"
b1 0"
1x
#5000
0x
#5500
bx000000100000000100000000 |
b100 }
bx0000000100000000 #"
bx0000000100000000 )"
b11 $"
b11 *"
b1010 2"
b11 !"
bx000000100000000100000000 {
b11 %"
b100 z
bx011100000000 ~
b1010 1"
b110 &"
b1010 ."
b1010 -"
b10 0"
1x
#6000
0x
#6500
bx00000011000000100000000100000000 |
bx00000011xxxxxxxxxxxxxxxxxxxxxxxx #"
bx00000011xxxxxxxxxxxxxxxxxxxxxxxx )"
b1000 $"
b1000 *"
b1010 2"
b100 !"
bx00000011000000100000000100000000 {
b100 %"
b100 z
bx0000011000000000 ~
b1010 1"
b111 &"
b1010 ."
b1010 -"
b11 0"
1x
#7000
0x
#7500
bx0000010000000011000000100000000100000000 |
b10100 }
bx #"
bx )"
b0 $"
b0 *"
b1010 2"
b101 !"
bx0000010000000011000000100000000100000000 {
b101 %"
b10100 z
bx01010000010100000000 ~
b1010 1"
b1000 &"
b1010 ."
b1010 -"
b100 0"
1x
#8000
0x
#8500
bx000001010000010000000011000000100000000100000000 |
b110100 }
b1010 2"
b110 !"
bx000001010000010000000011000000100000000100000000 {
b110 %"
b110100 z
bx011001000000010000000000 ~
b1010 1"
b1001 &"
b1010 ."
b1010 -"
b101 0"
1x
#9000
0x
#9500
b1010 2"
bx010100110000001100000000 ~
b1010 1"
b1010 &"
b1010 ."
b1010 -"
b110 0"
1x
#10000
0x
#10500
bx00000110000001010000010000000011000000100000000100000000 |
b1110100 }
b1010 2"
b111 !"
bx00000110000001010000010000000011000000100000000100000000 {
b111 %"
b1110100 z
bx1001010000100000001000000000 ~
b1010 1"
b1011 &"
b1010 ."
b1010 -"
b111 0"
1x
#11000
0x
#11500
bx0000011100000110000001010000010000000011000000100000000100000000 |
b11110100 }
b1010 2"
b1000 !"
bx0000011100000110000001010000010000000011000000100000000100000000 {
b1000 %"
b11110100 z
bx00111000001100010000000100000000 ~
b1010 1"
b1100 &"
b1010 ."
b1010 -"
b1000 0"
1x
#12000
0x
#12500
bx000010000000011100000110000001010000010000000011000000100000000100000000 |
b111100000 }
bx00000100xxxxxxxx00000010xxxxxxxxxxxxxxxx #"
bx00000100xxxxxxxx00000010xxxxxxxxxxxxxxxx )"
b10100 $"
b10100 *"
b1010 2"
b1001 !"
bx000010000000011100000110000001010000010000000011000000100000000100000000 {
b1001 %"
b111100000 z
bx100100100111001000000000000000000000 ~
b1010 1"
b1101 &"
b1010 ."
b1010 -"
b1001 0"
1x
#13000
0x
#13500
b1001000010000000011100000110000001010000010000000011000000100000000100000000 |
b1001xxxxxxxxxxxxxxxxxxxxxxxxxxxxxxxxxxxxxxxxxxxxxxxxxxxxxxxxxxxxxxxxxxxxxxxx #"
b1001xxxxxxxxxxxxxxxxxxxxxxxxxxxxxxxxxxxxxxxxxxxxxxxxxxxxxxxxxxxxxxxxxxxxxxxx )"
b1000000000 $"
b1000000000 *"
b1010 2"
b0 !"
b1001000010000000011100000110000001010000010000000011000000100000000100000000 {
b1010 %"
b111100000 z
b100000010110000100000000000000000000 ~
b1010 1"
b1110 &"
b1010 ."
b1010 -"
b1010 0"
1x
#14000
0x
#14500
b1001000010000000011100000110000001010000010000000011000000100000000100001010 |
b101000001 }
bx00000111xxxxxxxx00000101xxxxxxxxxxxxxxxxxxxxxxxxxxxxxxxxxxxxxxxx #"
bx00000111xxxxxxxx00000101xxxxxxxxxxxxxxxxxxxxxxxxxxxxxxxxxxxxxxxx )"
b10100000 $"
b10100000 *"
b1010 2"
b1 !"
b1001000010000000011100000110000001010000010000000011000000100000000100001010 {
b1011 %"
b101000001 z
b11100000101000000000000000000001001 ~
b1010 1"
b1111 &"
b1010 ."
b1010 -"
b1011 0"
1x
#15000
0x
#15500
b1001000010000000011100000110000001010000010000000011000000100000101100001010 |
b101000011 }
bx #"
bx )"
b0 $"
b0 *"
b1010 2"
b10 !"
b1001000010000000011100000110000001010000010000000011000000100000101100001010 {
b1100 %"
b101000011 z
b11000000100000000000000000001001000 ~
b1010 1"
b10000 &"
b1010 ."
b1010 -"
b1100 0"
1x
#16000
0x
#16500
b1001000010000000011100000110000001010000010000000011000011000000101100001010 |
b101000111 }
b1010 2"
b11 !"
b1001000010000000011100000110000001010000010000000011000011000000101100001010 {
b1101 %"
b101000111 z
b10100000011000000000000011000110111 ~
b1010 1"
b10001 &"
b1010 ."
b1010 -"
b1101 0"
1x
#17000
0x
#17500
b1001000010000000011100000110000001010000010000001101000011000000101100001010 |
bx00001101xxxxxxxxxxxxxxxxxxxxxxxx #"
bx00001101xxxxxxxxxxxxxxxxxxxxxxxx )"
b1000 $"
b1000 *"
b1010 2"
b100 !"
b1001000010000000011100000110000001010000010000001101000011000000101100001010 {
b1110 %"
b101000111 z
b10000000010000000000000010100100110 ~
b1010 1"
b10010 &"
b1010 ."
b1010 -"
b1110 0"
1x
#18000
0x
#18500
b1001000010000000011100000110000001010000111000001101000011000000101100001010 |
b101010111 }
bx #"
bx )"
b0 $"
b0 *"
b1010 2"
b101 !"
b1001000010000000011100000110000001010000111000001101000011000000101100001010 {
b1111 %"
b101010111 z
b1100000001000000010000010000010101 ~
b1010 1"
b10011 &"
b1010 ."
b1010 -"
b1111 0"
1x
#19000
0x
#19500
b1001000010000000011100000110000011110000111000001101000011000000101100001010 |
b100100101 }
bx00000110xxxxxxxx00001110xxxxxxxxxxxxxxxx00001011xxxxxxxx #"
bx00000110xxxxxxxx00001110xxxxxxxxxxxxxxxx00001011xxxxxxxx )"
b1010010 $"
b1010010 *"
b1010 2"
b110 !"
b1001000010000000011100000110000011110000111000001101000011000000101100001010 {
b10000 %"
b100100101 z
b1000000000001000000000001100000100 ~
b1010 1"
b10100 &"
b1010 ."
b1010 -"
b10000 0"
1x
#20000
0x
#20500
b1001000010000000011100010000000011110000111000001101000011000000101100001010 |
b101100101 }
bx #"
bx )"
b0 $"
b0 *"
b1010 2"
b111 !"
b1001000010000000011100010000000011110000111000001101000011000000101100001010 {
b10001 %"
b101100101 z
b100001000000100000000001000000011 ~
b1010 1"
b10101 &"
b1010 ."
b1010 -"
b10001 0"
1x
#21000
0x
#21500
b1001000010000001000100010000000011110000111000001101000011000000101100001010 |
b11000101 }
bx00001000xxxxxxxxxxxxxxxx00001111xxxxxxxxxxxxxxxxxxxxxxxxxxxxxxxxxxxxxxxx #"
bx00001000xxxxxxxxxxxxxxxx00001111xxxxxxxxxxxxxxxxxxxxxxxxxxxxxxxxxxxxxxxx )"
b100100000 $"
b100100000 *"
b1010 2"
b1000 !"
b1001000010000001000100010000000011110000111000001101000011000000101100001010 {
b10010 %"
b11000101 z
b100111000000000000000100000010 ~
b1010 1"
b10110 &"
b1010 ."
b1010 -"
b10010 0"
1x
#22000
0x
#22500
b1001000100100001000100010000000011110000111000001101000011000000101100001010 |
b11000001 }
bx00010010xxxxxxxxxxxxxxxxxxxxxxxxxxxxxxxxxxxxxxxx00001100xxxxxxxxxxxxxxxx #"
bx00010010xxxxxxxxxxxxxxxxxxxxxxxxxxxxxxxxxxxxxxxx00001100xxxxxxxxxxxxxxxx )"
b100000100 $"
b100000100 *"
b1010 2"
b1001 !"
b1001000100100001000100010000000011110000111000001101000011000000101100001010 {
b10011 %"
b11000001 z
b10110000000000000000000000001 ~
b1010 1"
b10111 &"
b1010 ."
b1010 -"
b10011 0"
1x
#23000
0x
#23500
b10011000100100001000100010000000011110000111000001101000011000000101100001010 |
b1001000000 }
bx00010001xxxxxxxxxxxxxxxxxxxxxxxxxxxxxxxxxxxxxxxxxxxxxxxx00001010 #"
bx00010001xxxxxxxxxxxxxxxxxxxxxxxxxxxxxxxxxxxxxxxxxxxxxxxx00001010 )"
b10000001 $"
b10000001 *"
b1010 2"
b0 !"
b10011000100100001000100010000000011110000111000001101000011000000101100001010 {
b10100 %"
b1001000000 z
b111000000000101000000000000000000000000 ~
b1010 1"
b11000 &"
b1010 ."
b1010 -"
b10100 0"
1x
#24000
0x
#24500
b10011000100100001000100010000000011110000111000001101000011000000101100010100 |
bx00010100 #"
bx00010100 )"
b1 $"
b1 *"
b1010 2"
b1 !"
b10011000100100001000100010000000011110000111000001101000011000000101100010100 {
b10101 %"
b1001000000 z
b110000000000100000000000000000000000000 ~
b1010 1"
b11001 &"
b1010 ."
b1010 -"
b10101 0"
1x
#25000
0x
#25500
b10011000100100001000100010000000011110000111000001101000011000001010100010100 |
b1001000010 }
bx #"
bx )"
b0 $"
b0 *"
b1010 2"
b10 !"
b10011000100100001000100010000000011110000111000001101000011000001010100010100 {
b10110 %"
b1001000010 z
b101000000000011000000000000000001010000 ~
b1010 1"
b11010 &"
b1010 ."
b1010 -"
b10110 0"
1x
#26000
0x
#26500
b10011000100100001000100010000000011110000111000001101000101100001010100010100 |
b1001000110 }
b1010 2"
b11 !"
b10011000100100001000100010000000011110000111000001101000101100001010100010100 {
b10111 %"
b1001000110 z
b100000000000010000000000000010101000000 ~
b1010 1"
b11011 &"
b1010 ."
b1010 -"
b10111 0"
1x
#27000
0x
#27500
b10011000100100001000100010000000011110000111000010111000101100001010100010100 |
b1001001110 }
b1010 2"
b100 !"
b10011000100100001000100010000000011110000111000010111000101100001010100010100 {
b11000 %"
b1001001110 z
b11000000000001000000000011010000110000 ~
b1010 1"
b11100 &"
b1010 ."
b1010 -"
b11000 0"
1x
#28000
0x
#28500
b10011000100100001000100010000000011110001100000010111000101100001010100010100 |
b1000011110 }
bx00010000xxxxxxxxxxxxxxxxxxxxxxxxxxxxxxxxxxxxxxxxxxxxxxxx #"
bx00010000xxxxxxxxxxxxxxxxxxxxxxxxxxxxxxxxxxxxxxxxxxxxxxxx )"
b1000000 $"
b1000000 *"
b1010 2"
b101 !"
b10011000100100001000100010000000011110001100000010111000101100001010100010100 {
b11001 %"
b1000011110 z
b10000000000000000010010010001100100000 ~
b1010 1"
b11101 &"
b1010 ."
b1010 -"
b11001 0"
1x
#29000
0x
#29500
b10011000100100001000100010000000110010001100000010111000101100001010100010100 |
b1000111110 }
bx #"
bx )"
b0 $"
b0 *"
b1010 2"
b110 !"
b10011000100100001000100010000000110010001100000010111000101100001010100010100 {
b11010 %"
b1000111110 z
b1000000000000011010000001001000010000 ~
b1010 1"
b11110 &"
b1010 ."
b1010 -"
b11010 0"
1x
#30000
0x
#30500
b10011000100100001000100011010000110010001100000010111000101100001010100010100 |
b1110100 }
b10011xxxxxxxxxxxxxxxxxxxxxxxxxxxxxxxxxxxxxxxx00010111xxxxxxxx00010101xxxxxxxx #"
b10011xxxxxxxxxxxxxxxxxxxxxxxxxxxxxxxxxxxxxxxx00010111xxxxxxxx00010101xxxxxxxx )"
b1000001010 $"
b1000001010 *"
b1010 2"
b111 !"
b10011000100100001000100011010000110010001100000010111000101100001010100010100 {
b11011 %"
b1110100 z
b111010101110000000100000000 ~
b1010 1"
b11111 &"
b1010 ."
b1010 -"
b11011 0"
1x
#31000
0x
#31500
b10011000100100001101100011010000110010001100000010111000101100001010100010100 |
b11110000 }
bx00010110xxxxxxxxxxxxxxxx #"
bx00010110xxxxxxxxxxxxxxxx )"
b100 $"
b100 *"
b1010 2"
b1000 !"
b10011000100100001101100011010000110010001100000010111000101100001010100010100 {
b11100 %"
b11110000 z
b10010110010001100000000000000000 ~
b1010 1"
b100000 &"
b1010 ."
b1010 -"
b11100 0"
1x
#32000
0x
